Workbook

Sheet README
B1: High-Mileage Vehicle Turnover Planner
B2: Built for a ~55,000 mi/yr driver in Hamilton County, Indiana
B4: HOW TO USE
B5: 1. Start on Inputs | C5: Every assumption in this workbook lives there. Change a number and the whole model recalculates. Nothing downstream is hardcoded.
B6: 2. Replace the purchase prices | C6: The prices on the Models tab are placeholder estimates, NOT quotes. Pull real local listings at your target odometer and overwrite them. This is the single biggest driver of the answer.
B7: 3. Read Models | C7: Head-to-head cost per mile across 70+ candidates, decomposed into depreciation, fuel, tires, maintenance, repair reserve, insurance, taxes, and cost of capital. Filter row 6 by Tier, Category, Fuel, or GVWR. Tier 1 is green (buy with confidence), Tier 2 amber (one caveat to manage), Tier 3 red (poor 180k-mile bet). Column AE ranks every model by cost per mile.
B8: 4. Read Strategies | C8: Compares buy-point / sell-point strategies (buy at 40k and sell at 150k vs. 180k, buy older, buy new, lease). Answers 'when do I turn over' rather than 'what do I buy'.
B9: 5. Run Tax | C9: Five ownership structures side by side, including Section 179 / bonus depreciation with the recapture cost modeled. Set employment type on Inputs first — it changes everything.
B10: 6. Log to Tracker | C10: Once a vehicle is in service, log every fuel stop, tire set, and repair. The summary block computes actual cost per mile so you can check the model against reality.
B12: COLOR LEGEND
B13: Blue text | C13: An input you can and should edit. Scenario levers and hardcoded assumptions.
B14: Black text | C14: A formula. Don't overwrite these — they'll stop recalculating.
B15: Green text | C15: A link pulling a value from another tab.
B16: Yellow fill | C16: A key assumption worth reviewing before you trust the output.
B18: READ THIS BEFORE TRUSTING THE TAX TAB
C19: • W-2 employees cannot deduct business mileage. The Tax Cuts and Jobs Act suspended unreimbursed employee business expenses, and the One Big Beautiful Bill Act (signed 7/4/2025) made that suspension permanent by amending IRC 67(g) to remove the sunset. IRS Publication 463 confirms it. If the driver is a W-2 employee, set Employment type to 'W-2' on Inputs and the model will correctly show a zero deduction benefit.
C20: • Only self-employment / Schedule C / business-entity miles produce a deduction. Set Employment type to 'Self-employed' only if that is actually the case.
C21: • Section 179 and bonus depreciation are a TIMING benefit at this turnover cadence, not a savings. Vehicles are Section 1245 property, so depreciation comes back as ORDINARY income on sale. Selling every ~30 months means recapture arrives fast. The Tax tab models this explicitly — look at the net, not the year-one deduction.
C22: • Claiming Section 179 or bonus on a vehicle permanently bars the standard mileage rate on that vehicle. There is no switching back.
C23: • None of this is tax advice. Confirm every figure with a CPA before filing. Indiana's treatment of business vehicle deductions may not track federal.
B25: MODEL LIMITATIONS
C26: • The depreciation curve comes from pooled asking-price cross-sections (~327,000 US listings), not the same VIN tracked over time. Different cars sit in each odometer band. Treat the coefficients as directional.
C27: • Purchase prices on the Models tab are estimates for illustration. Replace them with real listings.
C28: • Repair reserve rates are judgment calls calibrated to published major-repair incidence data. They are the softest numbers in the workbook — flex them on the Inputs tab to see how much the answer moves.
C29: • The finance cost uses an average-outstanding-balance approximation rather than a full amortization schedule. It is accurate to within a few hundred dollars over a 30-month cycle, not to the penny.
C30: • Insurance and Indiana excise figures are representative for Hamilton County, not a quote.

Sheet Inputs
B1: Inputs and Assumptions
B2: Blue cells are yours to change. Everything else in the workbook reads from here.
B4: DRIVING PATTERN & CYCLE
B5: Annual miles driven | C5: 55000 | D5: Stated: 50,000-60,000 per year. 55,000 is the midpoint.
B6: Buy odometer (miles) | C6: 40000 | D6: Odometer at purchase. The most important lever in the workbook.
B7: Sell odometer (miles) | C7: 180000 | D7: Odometer at disposal. Stated preference: 150,000-180,000.
B8: Miles per ownership cycle | C8: =C7-C6 -> 140000
B9: Years per cycle | C9: =IFERROR(C8/C5,0) -> 2.5454545
B10: Months per cycle | C10: =C9*12 -> 30.545455
B12: OPERATING COSTS
B13: Gasoline ($/gal) | C13: 3.55 | D13: Indiana average, AAA, early Aug 2026. National avg was $4.06-4.11.
B14: Diesel ($/gal) | C14: 5.35 | D14: Indiana average, AAA, early Aug 2026.
B15: Tire set - crossover ($ installed) | C15: 900 | D15: Range $700-$1,200 installed for crossover/SUV sizes.
B16: Tire set - truck ($ installed) | C16: 1300 | D16: Range $900-$1,500 for half-ton LT tires.
B17: Tire life (miles per set) | C17: 55000 | D17: Consumer Reports treadwear testing: 70,000-100,000 for premium touring. Derated for load and highway speed.
B18: Scheduled maintenance ($/mile) | C18: 0.08 | D18: Oil, brakes, plugs, fluids, transfer case. AAA's SUV line is $0.108-0.118/mi.
B19: Insurance ($/year) | C19: 1600 | D19: Indiana full coverage estimates range $1,009-$1,856 depending on source.
B20: Registration + excise + wheel tax ($/yr) | C20: 450 | D20: Hamilton County: $21.35 BMV base + $15 wheel tax + excise surtax. Excise declines as the vehicle ages.
B22: REPAIR RESERVE (the softest numbers here)
B23: Under 100,000 miles ($/mile) | C23: 0.03 | D23: Unscheduled repairs only. Scheduled work is on row 18.
B24: 100,000-150,000 miles ($/mile) | C24: 0.06 | D24: Failure incidence climbs sharply past 100k.
B25: Over 150,000 miles ($/mile) | C25: 0.1 | D25: Roughly 2/3 of vehicles over 100k hit a major repair averaging $3,847/yr per CoverageX (a warranty seller - read as a ceiling).
B26: Cycle miles in the <100k band | C26: =MAX(0,MIN(C7,100000)-C6) -> 60000
B27: Cycle miles in the 100k-150k band | C27: =MAX(0,MIN(C7,150000)-MAX(C6,100000)) -> 50000
B28: Cycle miles in the >150k band | C28: =MAX(0,C7-MAX(C6,150000)) -> 30000
B29: Blended repair reserve ($/mile) | C29: =IFERROR((C26*C23+C27*C24+C28*C25)/C8,0) -> 0.055714286 | D29: Weighted by how many cycle miles fall in each band.
B31: CAPITAL & FINANCING
B32: Financing mode | C32: Cash | D32: Pick one. Both are computed on the Models tab; this selects which flows into the total.
B33: Cash opportunity cost rate | C33: 0.045 | D33: Return foregone on capital tied up in the vehicle.
B34: Loan APR | C34: 0.065 | D34: Used-vehicle rate. Adjust to a real quote.
B35: Down payment % | C35: 0.2
B36: Average outstanding balance factor | C36: 0.55 | D36: Approximation. A loan held about half its term averages ~55% of principal outstanding. Avoids a full amortization schedule.
B38: TAX
B39: Employment type | C39: Self-employed | D39: W-2 employees get NO mileage deduction post-OBBBA (IRC 67(g), IRS Pub 463). Set this honestly - it zeroes out the tax benefit.
B40: Business use % | C40: 0.9 | D40: Must exceed 50% to claim Section 179 or bonus. Requires a contemporaneous mileage log.
B41: IRS standard mileage rate ($/mi) | C41: 0.74 | D41: 2026: 72.5c Jan-Jun (Notice 2026-10), raised to 76c Jul-Dec (Announcement 2026-11). 74c is the blended rate.
B42: Marginal federal income tax rate | C42: 0.24
B43: Self-employment tax effective rate | C43: 0.1413 | D43: 15.3% on 92.35% of net SE income, before the employer-half deduction.
B44: Indiana state income tax rate | C44: 0.0305
B45: Combined deduction benefit rate | C45: =IF(C39="Self-employed",C42+C43+C44,0) -> 0.4118 | D45: Zero for W-2 because the deduction does not exist. This is the whole ballgame.
B46: Indiana sales tax on purchase | C46: 0.07 | D46: One-time, at purchase.
B48: SECTION 179 / BONUS DEPRECIATION (2026)
B49: Bonus depreciation % | C49: 1 | D49: OBBBA sec. 70301 restored 100% permanently for property acquired and placed in service after 1/19/2025. Transition rules in Notice 2026-11.
B50: Section 179 cap - heavy SUV (6,001-14,000 lb) | C50: 31300 | D50: 2026 limit. Bonus has no such cap, so bonus is the mechanism above 6,000 lb GVWR.
B51: Sec. 280F first-year cap - light vehicle w/ bonus | C51: 20300 | D51: Rev. Proc. 2026-15. $12,300 without bonus. Applies at or below 6,000 lb GVWR.
B53: MODEL COMPARISON BASELINE
B54: Industry average 5-yr depreciation | C54: 0.418 | D54: iSeeCars 2026 study (950,000+ five-year-old vehicles, Mar 2025-Feb 2026). Baseline for each model's resale strength multiplier on the Models tab.

Sheet Depreciation
B1: Depreciation Engine
B2: Value retention as a function of odometer, converted to an index so it scales to any purchase price.
B4: Odometer | C4: Median listing price | D4: Retention index | E4: $ lost per 1,000 mi in band
B5: 0 | C5: 35000 | D5: =C5/$C$5 -> 1
B6: 10000 | C6: 33900 | D6: =C6/$C$5 -> 0.96857143 | E6: =IFERROR((C5-C6)/((B6-B5)/1000),0) -> 110
B7: 25000 | C7: 33480 | D7: =C7/$C$5 -> 0.95657143 | E7: =IFERROR((C6-C7)/((B7-B6)/1000),0) -> 28
B8: 50000 | C8: 26000 | D8: =C8/$C$5 -> 0.74285714 | E8: =IFERROR((C7-C8)/((B8-B7)/1000),0) -> 299.2
B9: 75000 | C9: 18995 | D9: =C9/$C$5 -> 0.54271429 | E9: =IFERROR((C8-C9)/((B9-B8)/1000),0) -> 280.2
B10: 100000 | C10: 14500 | D10: =C10/$C$5 -> 0.41428571 | E10: =IFERROR((C9-C10)/((B10-B9)/1000),0) -> 179.8
B11: 125000 | C11: 10950 | D11: =C11/$C$5 -> 0.31285714 | E11: =IFERROR((C10-C11)/((B11-B10)/1000),0) -> 142
B12: 150000 | C12: 8900 | D12: =C12/$C$5 -> 0.25428571 | E12: =IFERROR((C11-C12)/((B12-B11)/1000),0) -> 82
B13: 200000 | C13: 6450 | D13: =C13/$C$5 -> 0.18428571 | E13: =IFERROR((C12-C13)/((B13-B12)/1000),0) -> 49
B14: 250000 | C14: 4500 | D14: =C14/$C$5 -> 0.12857143 | E14: =IFERROR((C13-C14)/((B14-B13)/1000),0) -> 39
B15: Source: pooled analysis of ~327,000 US used listings (ForCar, Aug 2026). The $0 / $35,000 anchor is extrapolated to give the index a clean base. Asking-price cross-sections, not tracked VINs.
B18: APPLIED TO YOUR CYCLE
B19: Buy odometer | C19: =Inputs!$C$6 -> 40000 | D19: Pulled from Inputs.
B20: Sell odometer | C20: =Inputs!$C$7 -> 180000 | D20: Pulled from Inputs.
B21: Retention index at buy | C21: =IFERROR(INDEX($D$5:$D$14,MATCH($C$19,$B$5:$B$14,1))+($C$19-INDEX($B$5:$B$14,MATCH($C$19,$B$5:$B$14,1)))/(INDEX($B$5:$B$14,MATCH($C$19,$B$5:$B$14,1)+1)-INDEX($B$5:$B$14,MATCH($C$19,$B$5:$B$14,1)))*(INDEX($D$5:$D$14,MATCH($C$19,$B$5:$B$14,1)+1)-INDEX($D$5:$D$14,MATCH($C$19,$B$5:$B$14,1))),INDEX($D$5:$D$14,MATCH($C$19,$B$5:$B$14,1))) -> 0.82834286 | D21: Interpolated between the anchors above.
B22: Retention index at sell | C22: =IFERROR(INDEX($D$5:$D$14,MATCH($C$20,$B$5:$B$14,1))+($C$20-INDEX($B$5:$B$14,MATCH($C$20,$B$5:$B$14,1)))/(INDEX($B$5:$B$14,MATCH($C$20,$B$5:$B$14,1)+1)-INDEX($B$5:$B$14,MATCH($C$20,$B$5:$B$14,1)))*(INDEX($D$5:$D$14,MATCH($C$20,$B$5:$B$14,1)+1)-INDEX($D$5:$D$14,MATCH($C$20,$B$5:$B$14,1))),INDEX($D$5:$D$14,MATCH($C$20,$B$5:$B$14,1))) -> 0.21228571 | D22: Interpolated between the anchors above.
B23: Retention ratio (sell / buy) | C23: =IFERROR(C22/C21,0) -> 0.25627759 | D23: The fraction of the purchase price a market-average vehicle retains across your cycle. The Models tab multiplies this by a per-model resale strength factor.
B25: SCRATCH CALCULATOR
B26: Any odometer | C26: 120000
B27: Retention index there | C27: =IFERROR(INDEX($D$5:$D$14,MATCH($C$26,$B$5:$B$14,1))+($C$26-INDEX($B$5:$B$14,MATCH($C$26,$B$5:$B$14,1)))/(INDEX($B$5:$B$14,MATCH($C$26,$B$5:$B$14,1)+1)-INDEX($B$5:$B$14,MATCH($C$26,$B$5:$B$14,1)))*(INDEX($D$5:$D$14,MATCH($C$26,$B$5:$B$14,1)+1)-INDEX($D$5:$D$14,MATCH($C$26,$B$5:$B$14,1))),INDEX($D$5:$D$14,MATCH($C$26,$B$5:$B$14,1))) -> 0.33314286
B28: Est. value of a $35,000-when-new vehicle | C28: =C27*$C$5 -> 11660
B30: HOLD-PERIOD LOOKUP
B31: Hold period | C31: Sell odometer | D31: Retention index | E31: Retention ratio vs buy
B32: 1 year | C32: =Inputs!$C$6+1*Inputs!$C$5 -> 95000 | D32: =IFERROR(INDEX($D$5:$D$14,MATCH($C$32,$B$5:$B$14,1))+($C$32-INDEX($B$5:$B$14,MATCH($C$32,$B$5:$B$14,1)))/(INDEX($B$5:$B$14,MATCH($C$32,$B$5:$B$14,1)+1)-INDEX($B$5:$B$14,MATCH($C$32,$B$5:$B$14,1)))*(INDEX($D$5:$D$14,MATCH($C$32,$B$5:$B$14,1)+1)-INDEX($D$5:$D$14,MATCH($C$32,$B$5:$B$14,1))),INDEX($D$5:$D$14,MATCH($C$32,$B$5:$B$14,1))) -> 0.43997143 | E32: =IFERROR(D32/$C$21,0) -> 0.53114652
B33: 2 years | C33: =Inputs!$C$6+2*Inputs!$C$5 -> 150000 | D33: =IFERROR(INDEX($D$5:$D$14,MATCH($C$33,$B$5:$B$14,1))+($C$33-INDEX($B$5:$B$14,MATCH($C$33,$B$5:$B$14,1)))/(INDEX($B$5:$B$14,MATCH($C$33,$B$5:$B$14,1)+1)-INDEX($B$5:$B$14,MATCH($C$33,$B$5:$B$14,1)))*(INDEX($D$5:$D$14,MATCH($C$33,$B$5:$B$14,1)+1)-INDEX($D$5:$D$14,MATCH($C$33,$B$5:$B$14,1))),INDEX($D$5:$D$14,MATCH($C$33,$B$5:$B$14,1))) -> 0.25428571 | E33: =IFERROR(D33/$C$21,0) -> 0.30698124
B34: 2.5 years | C34: =Inputs!$C$6+2.5*Inputs!$C$5 -> 177500 | D34: =IFERROR(INDEX($D$5:$D$14,MATCH($C$34,$B$5:$B$14,1))+($C$34-INDEX($B$5:$B$14,MATCH($C$34,$B$5:$B$14,1)))/(INDEX($B$5:$B$14,MATCH($C$34,$B$5:$B$14,1)+1)-INDEX($B$5:$B$14,MATCH($C$34,$B$5:$B$14,1)))*(INDEX($D$5:$D$14,MATCH($C$34,$B$5:$B$14,1)+1)-INDEX($D$5:$D$14,MATCH($C$34,$B$5:$B$14,1))),INDEX($D$5:$D$14,MATCH($C$34,$B$5:$B$14,1))) -> 0.21578571 | E34: =IFERROR(D34/$C$21,0) -> 0.2605029
B35: 3 years | C35: =Inputs!$C$6+3*Inputs!$C$5 -> 205000 | D35: =IFERROR(INDEX($D$5:$D$14,MATCH($C$35,$B$5:$B$14,1))+($C$35-INDEX($B$5:$B$14,MATCH($C$35,$B$5:$B$14,1)))/(INDEX($B$5:$B$14,MATCH($C$35,$B$5:$B$14,1)+1)-INDEX($B$5:$B$14,MATCH($C$35,$B$5:$B$14,1)))*(INDEX($D$5:$D$14,MATCH($C$35,$B$5:$B$14,1)+1)-INDEX($D$5:$D$14,MATCH($C$35,$B$5:$B$14,1))),INDEX($D$5:$D$14,MATCH($C$35,$B$5:$B$14,1))) -> 0.17871429 | E35: =IFERROR(D35/$C$21,0) -> 0.21574917
B36: 4 years | C36: =Inputs!$C$6+4*Inputs!$C$5 -> 260000 | D36: =IFERROR(INDEX($D$5:$D$14,MATCH($C$36,$B$5:$B$14,1))+($C$36-INDEX($B$5:$B$14,MATCH($C$36,$B$5:$B$14,1)))/(INDEX($B$5:$B$14,MATCH($C$36,$B$5:$B$14,1)+1)-INDEX($B$5:$B$14,MATCH($C$36,$B$5:$B$14,1)))*(INDEX($D$5:$D$14,MATCH($C$36,$B$5:$B$14,1)+1)-INDEX($D$5:$D$14,MATCH($C$36,$B$5:$B$14,1))),INDEX($D$5:$D$14,MATCH($C$36,$B$5:$B$14,1))) -> 0.12857143 | E36: =IFERROR(D36/$C$21,0) -> 0.15521523
B37: Ratio = what fraction of the purchase price a market-average vehicle retains over that hold. The Models and HoldPeriod tabs multiply this by each model's resale-strength factor.

Sheet Models
A1: Model Comparison — Cost Per Mile
A2: Purchase prices in column G are PLACEHOLDER ESTIMATES, not quotes. Replace them with real local listings at your buy odometer before deciding anything.
A3: Use the filter arrows on row 6 to narrow by category, tier, fuel, or GVWR eligibility. Column AE ranks every model by total cost per mile (1 = cheapest).
A6: Model | B6: Category | C6: Tier | D6: 5-yr deprec. | E6: Deprec. source | F6: Resale mult. | G6: Purchase price | H6: Hwy MPG | I6: Fuel | J6: Tire class | K6: >6,000 lb GVWR | L6: 250k odds | M6: Odds study yr | N6: Known risk / red flag | O6: Est. resale | P6: Deprec. $ | Q6: Deprec. $/mi | R6: Fuel $/mi | S6: Tires $/mi | T6: Sched. maint $/mi | U6: Repair res. $/mi | V6: Insurance $/mi | W6: Reg/tax $/mi | X6: Sales tax $/mi | Y6: Capital $/mi (cash) | Z6: Capital $/mi (finance) | AA6: Capital $/mi (selected) | AB6: TOTAL $/mi | AC6: Cost per cycle | AD6: Cost per year | AE6: Rank | AF6: Reliability score | AG6: Comfort score | AH6: Cabin dB @55mph | AI6: dB source | AJ6: Resale @ 2 yr | AK6: Deprec. $/mi @ 2 yr
A7: Chevrolet Tahoe | B7: Full-size BOF SUV | C7: Tier 1 | D7: 0.453 | E7: iSeeCars 2026 | F7: =(1-D7)/(1-Inputs!$C$54) -> 0.93986254 | G7: 46000 | H7: 19.5 | I7: Gas | J7: Truck | K7: Yes | L7: 7.7% | M7: 2025 (base 4.8%) | N7: 5.3L AFM lifter/cam failure; 10L80 valve body. GM 10-spd more reliable than Ford's. | O7: =MIN(G7,G7*Depreciation!$C$23*F7) -> 11079.823 | P7: =G7-O7 -> 34920.177 | Q7: =IFERROR(P7/Inputs!$C$8,0) -> 0.24942984 | R7: =IFERROR(IF(I7="Diesel",Inputs!$C$14,Inputs!$C$13)/H7,0) -> 0.18205128 | S7: =IFERROR(IF(J7="Truck",Inputs!$C$16,Inputs!$C$15)/Inputs!$C$17,0) -> 0.023636364 | T7: =Inputs!$C$18 -> 0.08 | U7: =Inputs!$C$29 -> 0.055714286 | V7: =IFERROR(Inputs!$C$19/Inputs!$C$5,0) -> 0.029090909 | W7: =IFERROR(Inputs!$C$20/Inputs!$C$5,0) -> 0.0081818182 | X7: =IFERROR(G7*Inputs!$C$46/Inputs!$C$8,0) -> 0.023 | Y7: =IFERROR((G7+O7)/2*Inputs!$C$33*Inputs!$C$9/Inputs!$C$8,0) -> 0.023350837 | Z7: =IFERROR((G7*(1-Inputs!$C$35)*Inputs!$C$36*Inputs!$C$34*Inputs!$C$9+G7*Inputs!$C$35*Inputs!$C$33*Inputs!$C$9)/Inputs!$C$8,0) -> 0.031447273 | AA7: =IF(Inputs!$C$32="Cash",Y7,Z7) -> 0.023350837 | AB7: =Q7+R7+S7+T7+U7+V7+W7+X7+AA7 -> 0.67445533 | AC7: =AB7*Inputs!$C$8 -> 94423.747 | AD7: =AB7*Inputs!$C$5 -> 37095.043 | AE7: =RANK(AB7,$AB$7:$AB$82,1) -> 66 | AF7: 45.6 | AG7: 63.4 | AH7: 54.5 | AI7: measured | AJ7: =MIN(G7,G7*Depreciation!$E$33*F7) -> 13271.928 | AK7: =IFERROR((G7-AJ7)/(2*Inputs!$C$5),0) -> 0.29752793
A8: Chevrolet Tahoe 3.0L Duramax | B8: Full-size BOF SUV | C8: Tier 1 | D8: 0.453 | E8: iSeeCars 2026 | F8: =(1-D8)/(1-Inputs!$C$54) -> 0.93986254 | G8: 48000 | H8: 27 | I8: Diesel | J8: Truck | K8: Yes | L8: 7.7% | M8: 2025 (base 4.8%) | N8: CAUTION: at Indiana prices ($5.35 diesel vs $3.55 gas) the diesel costs MORE per mile to fuel than the gas V8 despite 27 vs 19.5 mpg. Only wins if the diesel premium narrows below ~$1.15/gal. | O8: =MIN(G8,G8*Depreciation!$C$23*F8) -> 11561.554 | P8: =G8-O8 -> 36438.446 | Q8: =IFERROR(P8/Inputs!$C$8,0) -> 0.26027461 | R8: =IFERROR(IF(I8="Diesel",Inputs!$C$14,Inputs!$C$13)/H8,0) -> 0.19814815 | S8: =IFERROR(IF(J8="Truck",Inputs!$C$16,Inputs!$C$15)/Inputs!$C$17,0) -> 0.023636364 | T8: =Inputs!$C$18 -> 0.08 | U8: =Inputs!$C$29 -> 0.055714286 | V8: =IFERROR(Inputs!$C$19/Inputs!$C$5,0) -> 0.029090909 | W8: =IFERROR(Inputs!$C$20/Inputs!$C$5,0) -> 0.0081818182 | X8: =IFERROR(G8*Inputs!$C$46/Inputs!$C$8,0) -> 0.024 | Y8: =IFERROR((G8+O8)/2*Inputs!$C$33*Inputs!$C$9/Inputs!$C$8,0) -> 0.02436609 | Z8: =IFERROR((G8*(1-Inputs!$C$35)*Inputs!$C$36*Inputs!$C$34*Inputs!$C$9+G8*Inputs!$C$35*Inputs!$C$33*Inputs!$C$9)/Inputs!$C$8,0) -> 0.032814545 | AA8: =IF(Inputs!$C$32="Cash",Y8,Z8) -> 0.02436609 | AB8: =Q8+R8+S8+T8+U8+V8+W8+X8+AA8 -> 0.70341223 | AC8: =AB8*Inputs!$C$8 -> 98477.712 | AD8: =AB8*Inputs!$C$5 -> 38687.673 | AE8: =RANK(AB8,$AB$7:$AB$82,1) -> 70 | AF8: 57.6 | AG8: 63.4 | AH8: 54.5 | AI8: measured | AJ8: =MIN(G8,G8*Depreciation!$E$33*F8) -> 13848.968 | AK8: =IFERROR((G8-AJ8)/(2*Inputs!$C$5),0) -> 0.31046393
A9: Chevrolet Suburban | B9: Full-size BOF SUV | C9: Tier 1 | D9: 0.556 | E9: iSeeCars 2025 | F9: =(1-D9)/(1-Inputs!$C$54) -> 0.7628866 | G9: 45000 | H9: 19 | I9: Gas | J9: Truck | K9: Yes | L9: 11.8% | M9: 2025 (base 4.8%) | N9: Same 5.3L AFM lifter risk as Tahoe. | O9: =MIN(G9,G9*Depreciation!$C$23*F9) -> 8797.9834 | P9: =G9-O9 -> 36202.017 | Q9: =IFERROR(P9/Inputs!$C$8,0) -> 0.25858583 | R9: =IFERROR(IF(I9="Diesel",Inputs!$C$14,Inputs!$C$13)/H9,0) -> 0.18684211 | S9: =IFERROR(IF(J9="Truck",Inputs!$C$16,Inputs!$C$15)/Inputs!$C$17,0) -> 0.023636364 | T9: =Inputs!$C$18 -> 0.08 | U9: =Inputs!$C$29 -> 0.055714286 | V9: =IFERROR(Inputs!$C$19/Inputs!$C$5,0) -> 0.029090909 | W9: =IFERROR(Inputs!$C$20/Inputs!$C$5,0) -> 0.0081818182 | X9: =IFERROR(G9*Inputs!$C$46/Inputs!$C$8,0) -> 0.0225 | Y9: =IFERROR((G9+O9)/2*Inputs!$C$33*Inputs!$C$9/Inputs!$C$8,0) -> 0.022008266 | Z9: =IFERROR((G9*(1-Inputs!$C$35)*Inputs!$C$36*Inputs!$C$34*Inputs!$C$9+G9*Inputs!$C$35*Inputs!$C$33*Inputs!$C$9)/Inputs!$C$8,0) -> 0.030763636 | AA9: =IF(Inputs!$C$32="Cash",Y9,Z9) -> 0.022008266 | AB9: =Q9+R9+S9+T9+U9+V9+W9+X9+AA9 -> 0.68655958 | AC9: =AB9*Inputs!$C$8 -> 96118.341 | AD9: =AB9*Inputs!$C$5 -> 37760.777 | AE9: =RANK(AB9,$AB$7:$AB$82,1) -> 68 | AF9: 45.6 | AG9: 64.4 | AH9: 54.4 | AI9: measured | AJ9: =MIN(G9,G9*Depreciation!$E$33*F9) -> 10538.634 | AK9: =IFERROR((G9-AJ9)/(2*Inputs!$C$5),0) -> 0.31328514
A10: GMC Yukon | B10: Full-size BOF SUV | C10: Tier 1 | D10: 0.48 | E10: iSeeCars 2026 | F10: =(1-D10)/(1-Inputs!$C$54) -> 0.89347079 | G10: 49000 | H10: 19 | I10: Gas | J10: Truck | K10: Yes | L10: 7.8% | M10: 2025 (base 4.8%) | N10: Same AFM lifter risk. GMC badge premium over Tahoe. | O10: =MIN(G10,G10*Depreciation!$C$23*F10) -> 11219.851 | P10: =G10-O10 -> 37780.149 | Q10: =IFERROR(P10/Inputs!$C$8,0) -> 0.26985821 | R10: =IFERROR(IF(I10="Diesel",Inputs!$C$14,Inputs!$C$13)/H10,0) -> 0.18684211 | S10: =IFERROR(IF(J10="Truck",Inputs!$C$16,Inputs!$C$15)/Inputs!$C$17,0) -> 0.023636364 | T10: =Inputs!$C$18 -> 0.08 | U10: =Inputs!$C$29 -> 0.055714286 | V10: =IFERROR(Inputs!$C$19/Inputs!$C$5,0) -> 0.029090909 | W10: =IFERROR(Inputs!$C$20/Inputs!$C$5,0) -> 0.0081818182 | X10: =IFERROR(G10*Inputs!$C$46/Inputs!$C$8,0) -> 0.0245 | Y10: =IFERROR((G10+O10)/2*Inputs!$C$33*Inputs!$C$9/Inputs!$C$8,0) -> 0.024635393 | Z10: =IFERROR((G10*(1-Inputs!$C$35)*Inputs!$C$36*Inputs!$C$34*Inputs!$C$9+G10*Inputs!$C$35*Inputs!$C$33*Inputs!$C$9)/Inputs!$C$8,0) -> 0.033498182 | AA10: =IF(Inputs!$C$32="Cash",Y10,Z10) -> 0.024635393 | AB10: =Q10+R10+S10+T10+U10+V10+W10+X10+AA10 -> 0.70245908 | AC10: =AB10*Inputs!$C$8 -> 98344.272 | AD10: =AB10*Inputs!$C$5 -> 38635.25 | AE10: =RANK(AB10,$AB$7:$AB$82,1) -> 69 | AF10: 29 | AG10: 63.4 | AH10: 54.5 | AI10: measured | AJ10: =MIN(G10,G10*Depreciation!$E$33*F10) -> 13439.66 | AK10: =IFERROR((G10-AJ10)/(2*Inputs!$C$5),0) -> 0.32327582
A11: GMC Yukon XL | B11: Full-size BOF SUV | C11: Tier 1 | D11: 0.48 | E11: iSeeCars 2026 | F11: =(1-D11)/(1-Inputs!$C$54) -> 0.89347079 | G11: 50000 | H11: 19 | I11: Gas | J11: Truck | K11: Yes | L11: 9.0% | M11: 2025 (base 4.8%) | N11: Same AFM lifter risk. | O11: =MIN(G11,G11*Depreciation!$C$23*F11) -> 11448.827 | P11: =G11-O11 -> 38551.173 | Q11: =IFERROR(P11/Inputs!$C$8,0) -> 0.27536552 | R11: =IFERROR(IF(I11="Diesel",Inputs!$C$14,Inputs!$C$13)/H11,0) -> 0.18684211 | S11: =IFERROR(IF(J11="Truck",Inputs!$C$16,Inputs!$C$15)/Inputs!$C$17,0) -> 0.023636364 | T11: =Inputs!$C$18 -> 0.08 | U11: =Inputs!$C$29 -> 0.055714286 | V11: =IFERROR(Inputs!$C$19/Inputs!$C$5,0) -> 0.029090909 | W11: =IFERROR(Inputs!$C$20/Inputs!$C$5,0) -> 0.0081818182 | X11: =IFERROR(G11*Inputs!$C$46/Inputs!$C$8,0) -> 0.025 | Y11: =IFERROR((G11+O11)/2*Inputs!$C$33*Inputs!$C$9/Inputs!$C$8,0) -> 0.025138157 | Z11: =IFERROR((G11*(1-Inputs!$C$35)*Inputs!$C$36*Inputs!$C$34*Inputs!$C$9+G11*Inputs!$C$35*Inputs!$C$33*Inputs!$C$9)/Inputs!$C$8,0) -> 0.034181818 | AA11: =IF(Inputs!$C$32="Cash",Y11,Z11) -> 0.025138157 | AB11: =Q11+R11+S11+T11+U11+V11+W11+X11+AA11 -> 0.70896916 | AC11: =AB11*Inputs!$C$8 -> 99255.682 | AD11: =AB11*Inputs!$C$5 -> 38993.304 | AE11: =RANK(AB11,$AB$7:$AB$82,1) -> 71 | AF11: 29 | AG11: 63.4 | AH11: 54.5 | AI11: measured | AJ11: =MIN(G11,G11*Depreciation!$E$33*F11) -> 13713.938 | AK11: =IFERROR((G11-AJ11)/(2*Inputs!$C$5),0) -> 0.32987329
A12: Ford Expedition | B12: Full-size BOF SUV | C12: Tier 2 | D12: 0.6 | E12: iSeeCars 2025 | F12: =(1-D12)/(1-Inputs!$C$54) -> 0.68728522 | G12: 43000 | H12: 18.5 | I12: Gas | J12: Truck | K12: Yes | L12: 19.9% | M12: 2023 (base 11.8%) | N12: Gen2 3.5 EcoBoost cam-phaser rattle 2018+ ($3.5k-$5.5k) AND 10R80 10-speed. Two known risks stacked. | O12: =MIN(G12,G12*Depreciation!$C$23*F12) -> 7573.8395 | P12: =G12-O12 -> 35426.16 | Q12: =IFERROR(P12/Inputs!$C$8,0) -> 0.253044 | R12: =IFERROR(IF(I12="Diesel",Inputs!$C$14,Inputs!$C$13)/H12,0) -> 0.19189189 | S12: =IFERROR(IF(J12="Truck",Inputs!$C$16,Inputs!$C$15)/Inputs!$C$17,0) -> 0.023636364 | T12: =Inputs!$C$18 -> 0.08 | U12: =Inputs!$C$29 -> 0.055714286 | V12: =IFERROR(Inputs!$C$19/Inputs!$C$5,0) -> 0.029090909 | W12: =IFERROR(Inputs!$C$20/Inputs!$C$5,0) -> 0.0081818182 | X12: =IFERROR(G12*Inputs!$C$46/Inputs!$C$8,0) -> 0.0215 | Y12: =IFERROR((G12+O12)/2*Inputs!$C$33*Inputs!$C$9/Inputs!$C$8,0) -> 0.020689298 | Z12: =IFERROR((G12*(1-Inputs!$C$35)*Inputs!$C$36*Inputs!$C$34*Inputs!$C$9+G12*Inputs!$C$35*Inputs!$C$33*Inputs!$C$9)/Inputs!$C$8,0) -> 0.029396364 | AA12: =IF(Inputs!$C$32="Cash",Y12,Z12) -> 0.020689298 | AB12: =Q12+R12+S12+T12+U12+V12+W12+X12+AA12 -> 0.68374857 | AC12: =AB12*Inputs!$C$8 -> 95724.8 | AD12: =AB12*Inputs!$C$5 -> 37606.171 | AE12: =RANK(AB12,$AB$7:$AB$82,1) -> 67 | AF12: 52.7 | AG12: 64.4 | AH12: 54.4 | AI12: measured | AJ12: =MIN(G12,G12*Depreciation!$E$33*F12) -> 9072.2977 | AK12: =IFERROR((G12-AJ12)/(2*Inputs!$C$5),0) -> 0.30843366
A13: Toyota Sequoia (pre-2023 5.7 V8) | B13: Full-size BOF SUV | C13: Tier 1 | D13: 0.42 | E13: segment est. | F13: =(1-D13)/(1-Inputs!$C$54) -> 0.99656357 | G13: 46000 | H13: 15.5 | I13: Gas | J13: Truck | K13: Yes | L13: 39.1% | M13: 2025 (base 4.8%) | N13: #1 longest-lasting vehicle in the 2025 study, 8x the industry average. Worst fuel economy here. | O13: =MIN(G13,G13*Depreciation!$C$23*F13) -> 11748.258 | P13: =G13-O13 -> 34251.742 | Q13: =IFERROR(P13/Inputs!$C$8,0) -> 0.2446553 | R13: =IFERROR(IF(I13="Diesel",Inputs!$C$14,Inputs!$C$13)/H13,0) -> 0.22903226 | S13: =IFERROR(IF(J13="Truck",Inputs!$C$16,Inputs!$C$15)/Inputs!$C$17,0) -> 0.023636364 | T13: =Inputs!$C$18 -> 0.08 | U13: =Inputs!$C$29 -> 0.055714286 | V13: =IFERROR(Inputs!$C$19/Inputs!$C$5,0) -> 0.029090909 | W13: =IFERROR(Inputs!$C$20/Inputs!$C$5,0) -> 0.0081818182 | X13: =IFERROR(G13*Inputs!$C$46/Inputs!$C$8,0) -> 0.023 | Y13: =IFERROR((G13+O13)/2*Inputs!$C$33*Inputs!$C$9/Inputs!$C$8,0) -> 0.023624287 | Z13: =IFERROR((G13*(1-Inputs!$C$35)*Inputs!$C$36*Inputs!$C$34*Inputs!$C$9+G13*Inputs!$C$35*Inputs!$C$33*Inputs!$C$9)/Inputs!$C$8,0) -> 0.031447273 | AA13: =IF(Inputs!$C$32="Cash",Y13,Z13) -> 0.023624287 | AB13: =Q13+R13+S13+T13+U13+V13+W13+X13+AA13 -> 0.71693522 | AC13: =AB13*Inputs!$C$8 -> 100370.93 | AD13: =AB13*Inputs!$C$5 -> 39431.437 | AE13: =RANK(AB13,$AB$7:$AB$82,1) -> 73 | AF13: 100 | AG13: 52.3 | AH13: 55.7 | AI13: measured | AJ13: =MIN(G13,G13*Depreciation!$E$33*F13) -> 14072.611 | AK13: =IFERROR((G13-AJ13)/(2*Inputs!$C$5),0) -> 0.29024899
A14: Nissan Armada | B14: Full-size BOF SUV | C14: Tier 2 | D14: 0.6 | E14: iSeeCars 2025 | F14: =(1-D14)/(1-Inputs!$C$54) -> 0.68728522 | G14: 32000 | H14: 17 | I14: Gas | J14: Truck | K14: Yes | L14: 5.8% | M14: 2025 (base 4.8%) | N14: 5.6L V8 + 7-spd conventional, NOT a CVT. Durable but weak resale - that's the cheap-buy opening. | O14: =MIN(G14,G14*Depreciation!$C$23*F14) -> 5636.3457 | P14: =G14-O14 -> 26363.654 | Q14: =IFERROR(P14/Inputs!$C$8,0) -> 0.18831182 | R14: =IFERROR(IF(I14="Diesel",Inputs!$C$14,Inputs!$C$13)/H14,0) -> 0.20882353 | S14: =IFERROR(IF(J14="Truck",Inputs!$C$16,Inputs!$C$15)/Inputs!$C$17,0) -> 0.023636364 | T14: =Inputs!$C$18 -> 0.08 | U14: =Inputs!$C$29 -> 0.055714286 | V14: =IFERROR(Inputs!$C$19/Inputs!$C$5,0) -> 0.029090909 | W14: =IFERROR(Inputs!$C$20/Inputs!$C$5,0) -> 0.0081818182 | X14: =IFERROR(G14*Inputs!$C$46/Inputs!$C$8,0) -> 0.016 | Y14: =IFERROR((G14+O14)/2*Inputs!$C$33*Inputs!$C$9/Inputs!$C$8,0) -> 0.015396687 | Z14: =IFERROR((G14*(1-Inputs!$C$35)*Inputs!$C$36*Inputs!$C$34*Inputs!$C$9+G14*Inputs!$C$35*Inputs!$C$33*Inputs!$C$9)/Inputs!$C$8,0) -> 0.021876364 | AA14: =IF(Inputs!$C$32="Cash",Y14,Z14) -> 0.015396687 | AB14: =Q14+R14+S14+T14+U14+V14+W14+X14+AA14 -> 0.62515541 | AC14: =AB14*Inputs!$C$8 -> 87521.757 | AD14: =AB14*Inputs!$C$5 -> 34383.548 | AE14: =RANK(AB14,$AB$7:$AB$82,1) -> 64 | AF14: 86.4 | AG14: 58.8 | AH14: 55 | AI14: measured | AJ14: =MIN(G14,G14*Depreciation!$E$33*F14) -> 6751.4774 | AK14: =IFERROR((G14-AJ14)/(2*Inputs!$C$5),0) -> 0.22953202
A15: Cadillac Escalade | B15: Full-size BOF SUV | C15: Tier 3 | D15: 0.618 | E15: iSeeCars 2025 | F15: =(1-D15)/(1-Inputs!$C$54) -> 0.65635739 | G15: 70000 | H15: 17 | I15: Gas | J15: Truck | K15: Yes | L15: 6.8% | M15: 2025 ESV (base 4.8%) | N15: Luxury depreciation plus air suspension and electronics. Wrong tool at this mileage. | O15: =MIN(G15,G15*Depreciation!$C$23*F15) -> 11774.678 | P15: =G15-O15 -> 58225.322 | Q15: =IFERROR(P15/Inputs!$C$8,0) -> 0.41589515 | R15: =IFERROR(IF(I15="Diesel",Inputs!$C$14,Inputs!$C$13)/H15,0) -> 0.20882353 | S15: =IFERROR(IF(J15="Truck",Inputs!$C$16,Inputs!$C$15)/Inputs!$C$17,0) -> 0.023636364 | T15: =Inputs!$C$18 -> 0.08 | U15: =Inputs!$C$29 -> 0.055714286 | V15: =IFERROR(Inputs!$C$19/Inputs!$C$5,0) -> 0.029090909 | W15: =IFERROR(Inputs!$C$20/Inputs!$C$5,0) -> 0.0081818182 | X15: =IFERROR(G15*Inputs!$C$46/Inputs!$C$8,0) -> 0.035 | Y15: =IFERROR((G15+O15)/2*Inputs!$C$33*Inputs!$C$9/Inputs!$C$8,0) -> 0.033453278 | Z15: =IFERROR((G15*(1-Inputs!$C$35)*Inputs!$C$36*Inputs!$C$34*Inputs!$C$9+G15*Inputs!$C$35*Inputs!$C$33*Inputs!$C$9)/Inputs!$C$8,0) -> 0.047854545 | AA15: =IF(Inputs!$C$32="Cash",Y15,Z15) -> 0.033453278 | AB15: =Q15+R15+S15+T15+U15+V15+W15+X15+AA15 -> 0.88979534 | AC15: =AB15*Inputs!$C$8 -> 124571.35 | AD15: =AB15*Inputs!$C$5 -> 48938.744 | AE15: =RANK(AB15,$AB$7:$AB$82,1) -> 76 | AF15: 44.1 | AG15: 54.2 | AH15: 55.5 | AI15: measured | AJ15: =MIN(G15,G15*Depreciation!$E$33*F15) -> 14104.258 | AK15: =IFERROR((G15-AJ15)/(2*Inputs!$C$5),0) -> 0.50814311
A16: Jeep Grand Wagoneer | B16: Full-size BOF SUV | C16: Tier 3 | D16: 0.56 | E16: estimate | F16: =(1-D16)/(1-Inputs!$C$54) -> 0.75601375 | G16: 54000 | H16: 16.5 | I16: Gas | J16: Truck | K16: Yes | L16: n/a | M16: not available | N16: New platform, thin high-mileage data, luxury electronics risk. | O16: =MIN(G16,G16*Depreciation!$C$23*F16) -> 10462.467 | P16: =G16-O16 -> 43537.533 | Q16: =IFERROR(P16/Inputs!$C$8,0) -> 0.31098238 | R16: =IFERROR(IF(I16="Diesel",Inputs!$C$14,Inputs!$C$13)/H16,0) -> 0.21515152 | S16: =IFERROR(IF(J16="Truck",Inputs!$C$16,Inputs!$C$15)/Inputs!$C$17,0) -> 0.023636364 | T16: =Inputs!$C$18 -> 0.08 | U16: =Inputs!$C$29 -> 0.055714286 | V16: =IFERROR(Inputs!$C$19/Inputs!$C$5,0) -> 0.029090909 | W16: =IFERROR(Inputs!$C$20/Inputs!$C$5,0) -> 0.0081818182 | X16: =IFERROR(G16*Inputs!$C$46/Inputs!$C$8,0) -> 0.027 | Y16: =IFERROR((G16+O16)/2*Inputs!$C$33*Inputs!$C$9/Inputs!$C$8,0) -> 0.026371009 | Z16: =IFERROR((G16*(1-Inputs!$C$35)*Inputs!$C$36*Inputs!$C$34*Inputs!$C$9+G16*Inputs!$C$35*Inputs!$C$33*Inputs!$C$9)/Inputs!$C$8,0) -> 0.036916364 | AA16: =IF(Inputs!$C$32="Cash",Y16,Z16) -> 0.026371009 | AB16: =Q16+R16+S16+T16+U16+V16+W16+X16+AA16 -> 0.77612828 | AC16: =AB16*Inputs!$C$8 -> 108657.96 | AD16: =AB16*Inputs!$C$5 -> 42687.055 | AE16: =RANK(AB16,$AB$7:$AB$82,1) -> 74 | AF16: 28.4 | AG16: 31 | AH16: 58 | AI16: measured | AJ16: =MIN(G16,G16*Depreciation!$E$33*F16) -> 12532.43 | AK16: =IFERROR((G16-AJ16)/(2*Inputs!$C$5),0) -> 0.37697791
A17: Jeep Grand Cherokee | B17: Mid-size SUV | C17: Tier 2 | D17: 0.51 | E17: 2025 segment | F17: =(1-D17)/(1-Inputs!$C$54) -> 0.8419244 | G17: 32000 | H17: 23 | I17: Gas | J17: Crossover | K17: Yes | L17: n/a | M17: not available | N17: ZF 8HP is strong BUT flush it at 60k - Jeep calls it lifetime fill. 2021+ WL 850RE early clutch faults. | O17: =MIN(G17,G17*Depreciation!$C$23*F17) -> 6904.5235 | P17: =G17-O17 -> 25095.477 | Q17: =IFERROR(P17/Inputs!$C$8,0) -> 0.1792534 | R17: =IFERROR(IF(I17="Diesel",Inputs!$C$14,Inputs!$C$13)/H17,0) -> 0.15434783 | S17: =IFERROR(IF(J17="Truck",Inputs!$C$16,Inputs!$C$15)/Inputs!$C$17,0) -> 0.016363636 | T17: =Inputs!$C$18 -> 0.08 | U17: =Inputs!$C$29 -> 0.055714286 | V17: =IFERROR(Inputs!$C$19/Inputs!$C$5,0) -> 0.029090909 | W17: =IFERROR(Inputs!$C$20/Inputs!$C$5,0) -> 0.0081818182 | X17: =IFERROR(G17*Inputs!$C$46/Inputs!$C$8,0) -> 0.016 | Y17: =IFERROR((G17+O17)/2*Inputs!$C$33*Inputs!$C$9/Inputs!$C$8,0) -> 0.015915487 | Z17: =IFERROR((G17*(1-Inputs!$C$35)*Inputs!$C$36*Inputs!$C$34*Inputs!$C$9+G17*Inputs!$C$35*Inputs!$C$33*Inputs!$C$9)/Inputs!$C$8,0) -> 0.021876364 | AA17: =IF(Inputs!$C$32="Cash",Y17,Z17) -> 0.015915487 | AB17: =Q17+R17+S17+T17+U17+V17+W17+X17+AA17 -> 0.55486737 | AC17: =AB17*Inputs!$C$8 -> 77681.431 | AD17: =AB17*Inputs!$C$5 -> 30517.705 | AE17: =RANK(AB17,$AB$7:$AB$82,1) -> 42 | AF17: 30.4 | AG17: 64.8 | AH17: 55 | AI17: estimated | AJ17: =MIN(G17,G17*Depreciation!$E$33*F17) -> 8270.5598 | AK17: =IFERROR((G17-AJ17)/(2*Inputs!$C$5),0) -> 0.21572218
A18: Jeep Grand Cherokee L | B18: 3-row crossover | C18: Tier 2 | D18: 0.51 | E18: 2025 segment | F18: =(1-D18)/(1-Inputs!$C$54) -> 0.8419244 | G18: 38000 | H18: 22.5 | I18: Gas | J18: Crossover | K18: Yes | L18: n/a | M18: not available | N18: Same ZF 8HP / 850RE concerns as Grand Cherokee. | O18: =MIN(G18,G18*Depreciation!$C$23*F18) -> 8199.1216 | P18: =G18-O18 -> 29800.878 | Q18: =IFERROR(P18/Inputs!$C$8,0) -> 0.21286342 | R18: =IFERROR(IF(I18="Diesel",Inputs!$C$14,Inputs!$C$13)/H18,0) -> 0.15777778 | S18: =IFERROR(IF(J18="Truck",Inputs!$C$16,Inputs!$C$15)/Inputs!$C$17,0) -> 0.016363636 | T18: =Inputs!$C$18 -> 0.08 | U18: =Inputs!$C$29 -> 0.055714286 | V18: =IFERROR(Inputs!$C$19/Inputs!$C$5,0) -> 0.029090909 | W18: =IFERROR(Inputs!$C$20/Inputs!$C$5,0) -> 0.0081818182 | X18: =IFERROR(G18*Inputs!$C$46/Inputs!$C$8,0) -> 0.019 | Y18: =IFERROR((G18+O18)/2*Inputs!$C$33*Inputs!$C$9/Inputs!$C$8,0) -> 0.018899641 | Z18: =IFERROR((G18*(1-Inputs!$C$35)*Inputs!$C$36*Inputs!$C$34*Inputs!$C$9+G18*Inputs!$C$35*Inputs!$C$33*Inputs!$C$9)/Inputs!$C$8,0) -> 0.025978182 | AA18: =IF(Inputs!$C$32="Cash",Y18,Z18) -> 0.018899641 | AB18: =Q18+R18+S18+T18+U18+V18+W18+X18+AA18 -> 0.59789148 | AC18: =AB18*Inputs!$C$8 -> 83704.808 | AD18: =AB18*Inputs!$C$5 -> 32884.032 | AE18: =RANK(AB18,$AB$7:$AB$82,1) -> 56 | AF18: 30.4 | AG18: 64.8 | AH18: 55 | AI18: estimated | AJ18: =MIN(G18,G18*Depreciation!$E$33*F18) -> 9821.2897 | AK18: =IFERROR((G18-AJ18)/(2*Inputs!$C$5),0) -> 0.25617009
... A82: Ram 2500 (Cummins) | B82: Heavy-duty truck | C82: Tier 2 | D82: 0.4 | E82: estimate | F82: =(1-D82)/(1-Inputs!$C$54) -> 1.0309278 | G82: 52000 | H82: 19 | I82: Diesel | J82: Truck | K82: Yes (10,000) | L82: 17.3% | M82: 2025 (base 4.8%) | N82: Cummins I6 durability is legendary. CP4 pump risk on 2019+. Diesel fuel cost is the drag. | O82: =MIN(G82,G82*Depreciation!$C$23*F82) -> 13738.593 | P82: =G82-O82 -> 38261.407 | Q82: =IFERROR(P82/Inputs!$C$8,0) -> 0.27329577 | R82: =IFERROR(IF(I82="Diesel",Inputs!$C$14,Inputs!$C$13)/H82,0) -> 0.28157895 | S82: =IFERROR(IF(J82="Truck",Inputs!$C$16,Inputs!$C$15)/Inputs!$C$17,0) -> 0.023636364 | T82: =Inputs!$C$18 -> 0.08 | U82: =Inputs!$C$29 -> 0.055714286 | V82: =IFERROR(Inputs!$C$19/Inputs!$C$5,0) -> 0.029090909 | W82: =IFERROR(Inputs!$C$20/Inputs!$C$5,0) -> 0.0081818182 | X82: =IFERROR(G82*Inputs!$C$46/Inputs!$C$8,0) -> 0.026 | Y82: =IFERROR((G82+O82)/2*Inputs!$C$33*Inputs!$C$9/Inputs!$C$8,0) -> 0.026893061 | Z82: =IFERROR((G82*(1-Inputs!$C$35)*Inputs!$C$36*Inputs!$C$34*Inputs!$C$9+G82*Inputs!$C$35*Inputs!$C$33*Inputs!$C$9)/Inputs!$C$8,0) -> 0.035549091 | AA82: =IF(Inputs!$C$32="Cash",Y82,Z82) -> 0.026893061 | AB82: =Q82+R82+S82+T82+U82+V82+W82+X82+AA82 -> 0.80439115 | AC82: =AB82*Inputs!$C$8 -> 112614.76 | AD82: =AB82*Inputs!$C$5 -> 44241.513 | AE82: =RANK(AB82,$AB$7:$AB$82,1) -> 75 | AF82: 33.4 | AG82: 32.9 | AH82: 57.8 | AI82: measured | AJ82: =MIN(G82,G82*Depreciation!$E$33*F82) -> 16456.726 | AK82: =IFERROR((G82-AJ82)/(2*Inputs!$C$5),0) -> 0.32312067
A84: TIER KEY
A85: Tier 1 | B85: Proven high-mileage durability, no transmission red flag. Buy with confidence.
A86: Tier 2 | B86: Viable with a caveat — one component to watch, a fuel-cost drag, or a service requirement you must document.
A87: Tier 3 | B87: Poor 180,000-mile bet. Documented transmission or turbo weakness, or fuel/luxury costs that dominate. Avoid or research hard.
A89: • DEPRECIATION FIGURES MIX STUDY YEARS AND ARE NOT DIRECTLY COMPARABLE. The iSeeCars industry baseline moved: 38.8% (2023), 45.6% (2025), 41.8% (2026). Column E names the source for every row. A 2025-study figure sits against a 45.6% baseline; a 2026-study figure against 41.8%. Rows marked '2025 segment' or 'estimate' had no individual breakout — treat those resale multipliers as weak.
A90: • 250,000-MILE ODDS ARE ALSO NOT COMPARABLE ACROSS YEARS. The baseline collapsed from 11.8% (2023) to 8.6% (2024) to 4.8% (2025). Column M gives the study year and that year's baseline so you can read each figure against the right denominator. Rankings hold across years even though absolute percentages do not.
A91: • CVT WARNING. Nissan Rogue (2014-2018), Pathfinder (2013-2020), and Murano use the Jatco CVT that produced a $277.7 million class settlement (Stringer v. Nissan) with powertrain warranty extended to 84 months / 84,000 miles. Subaru and Honda CVTs have better records but still need fluid every 30-60k. Toyota, Lexus, and Ford hybrid 'eCVT' units are planetary power-split devices, NOT belt CVTs — they are among the most durable transmissions on the road. Do not confuse the two.
A92: • OTHER TRANSMISSION RED FLAGS. ZF 9HP (Jeep Cherokee, Compass, Renegade): 7,000+ complaints on 2014-15 Cherokees alone, 82,000-unit recall. Ford 10R80 10-speed (Explorer, Ranger, F-150, Expedition): rebuild $3,800-$5,200. GM's 10L80 has a notably better record than Ford's 10R80.
A93: • SECTION 179 SURPRISE. The Kia Telluride (5,776-5,917 lb) and Hyundai Palisade (5,700-5,900 lb) are UNDER 6,000 lb GVWR despite their size, so they do NOT qualify for the heavy-vehicle treatment. Honda Pilot, Chevy Traverse, GMC Acadia, and Grand Highlander straddle the line by trim and drivetrain. The door-jamb Safety Compliance sticker is the only authoritative source — pull a photo before you buy.
A94: • FULL-SIZE SUV MATH. At 55,000 mi/yr, a 17 mpg full-size SUV burns about 3,235 gallons a year against 1,964 for a 28 mpg crossover. At $3.55/gal that is roughly a $4,500/yr fuel penalty. Best-in-segment resale recovers only part of it. A gas Tahoe/Yukon is justified only if you genuinely need the tow rating, eight or nine seats, or body-on-frame durability. The 3.0L Duramax is NOT the escape hatch it looks like: at Indiana's $5.35 diesel vs $3.55 gas, 27 mpg diesel costs $0.198/mi against $0.182/mi for the 19.5 mpg gas V8. The diesel only wins if the per-gallon premium falls below about $1.15. Check both fuel prices before assuming diesel saves money.

Sheet Strategies
A1: Turnover Strategy Comparison
A2: Same cost engine, different buy and sell points. Answers 'when do I turn over', not 'what do I buy'.
A4: Strategy | B4: Buy odo | C4: Sell odo | D4: Purchase price | E4: Cycle miles | F4: Years | G4: Idx buy | H4: Idx sell | I4: Est. resale | J4: Deprec. $ | K4: Deprec. $/mi | L4: Mi <100k | M4: Mi 100-150k | N4: Mi >150k | O4: Repair $/mi | P4: Fuel $/mi | Q4: Tires $/mi | R4: Maint $/mi | S4: Ins+reg $/mi | T4: Sales tax $/mi | U4: Capital $/mi | V4: TOTAL $/mi | W4: Cost per year
A5: A — Buy 40k, sell 150k (24 mo) | B5: 40000 | C5: 150000 | D5: 26000 | E5: =C5-B5 -> 110000 | F5: =IFERROR(E5/Inputs!$C$5,0) -> 2 | G5: =IFERROR(INDEX(Depreciation!$D$5:$D$14,MATCH(B5,Depreciation!$B$5:$B$14,1))+(B5-INDEX(Depreciation!$B$5:$B$14,MATCH(B5,Depreciation!$B$5:$B$14,1)))/(INDEX(Depreciation!$B$5:$B$14,MATCH(B5,Depreciation!$B$5:$B$14,1)+1)-INDEX(Depreciation!$B$5:$B$14,MATCH(B5,Depreciation!$B$5:$B$14,1)))*(INDEX(Depreciation!$D$5:$D$14,MATCH(B5,Depreciation!$B$5:$B$14,1)+1)-INDEX(Depreciation!$D$5:$D$14,MATCH(B5,Depreciation!$B$5:$B$14,1))),INDEX(Depreciation!$D$5:$D$14,MATCH(B5,Depreciation!$B$5:$B$14,1))) -> 0.82834286 | H5: =IFERROR(INDEX(Depreciation!$D$5:$D$14,MATCH(C5,Depreciation!$B$5:$B$14,1))+(C5-INDEX(Depreciation!$B$5:$B$14,MATCH(C5,Depreciation!$B$5:$B$14,1)))/(INDEX(Depreciation!$B$5:$B$14,MATCH(C5,Depreciation!$B$5:$B$14,1)+1)-INDEX(Depreciation!$B$5:$B$14,MATCH(C5,Depreciation!$B$5:$B$14,1)))*(INDEX(Depreciation!$D$5:$D$14,MATCH(C5,Depreciation!$B$5:$B$14,1)+1)-INDEX(Depreciation!$D$5:$D$14,MATCH(C5,Depreciation!$B$5:$B$14,1))),INDEX(Depreciation!$D$5:$D$14,MATCH(C5,Depreciation!$B$5:$B$14,1))) -> 0.25428571 | I5: =IFERROR(MIN(D5,D5*H5/G5),0) -> 7981.5121 | J5: =D5-I5 -> 18018.488 | K5: =IFERROR(J5/E5,0) -> 0.16380444 | L5: =MAX(0,MIN(C5,100000)-B5) -> 60000 | M5: =MAX(0,MIN(C5,150000)-MAX(B5,100000)) -> 50000 | N5: =MAX(0,C5-MAX(B5,150000)) -> 0 | O5: =IFERROR((L5*Inputs!$C$23+M5*Inputs!$C$24+N5*Inputs!$C$25)/E5,0) -> 0.043636364 | P5: =IFERROR(Inputs!$C$13/24,0) -> 0.14791667 | Q5: =IFERROR(Inputs!$C$15/Inputs!$C$17,0) -> 0.016363636 | R5: =Inputs!$C$18 -> 0.08 | S5: =IFERROR((Inputs!$C$19+Inputs!$C$20)/Inputs!$C$5,0) -> 0.037272727 | T5: =IFERROR(D5*Inputs!$C$46/E5,0) -> 0.016545455 | U5: =IFERROR(IF(Inputs!$C$32="Cash",(D5+I5)/2*Inputs!$C$33*F5,(D5*(1-Inputs!$C$35)*Inputs!$C$36*Inputs!$C$34*F5+D5*Inputs!$C$35*Inputs!$C$33*F5))/E5,0) -> 0.013901528 | V5: =K5+O5+P5+Q5+R5+S5+T5+U5 -> 0.51944081 | W5: =V5*Inputs!$C$5 -> 28569.245
A6: B — Buy 40k, sell 180k (30 mo) | B6: 40000 | C6: 180000 | D6: 26000 | E6: =C6-B6 -> 140000 | F6: =IFERROR(E6/Inputs!$C$5,0) -> 2.5454545 | G6: =IFERROR(INDEX(Depreciation!$D$5:$D$14,MATCH(B6,Depreciation!$B$5:$B$14,1))+(B6-INDEX(Depreciation!$B$5:$B$14,MATCH(B6,Depreciation!$B$5:$B$14,1)))/(INDEX(Depreciation!$B$5:$B$14,MATCH(B6,Depreciation!$B$5:$B$14,1)+1)-INDEX(Depreciation!$B$5:$B$14,MATCH(B6,Depreciation!$B$5:$B$14,1)))*(INDEX(Depreciation!$D$5:$D$14,MATCH(B6,Depreciation!$B$5:$B$14,1)+1)-INDEX(Depreciation!$D$5:$D$14,MATCH(B6,Depreciation!$B$5:$B$14,1))),INDEX(Depreciation!$D$5:$D$14,MATCH(B6,Depreciation!$B$5:$B$14,1))) -> 0.82834286 | H6: =IFERROR(INDEX(Depreciation!$D$5:$D$14,MATCH(C6,Depreciation!$B$5:$B$14,1))+(C6-INDEX(Depreciation!$B$5:$B$14,MATCH(C6,Depreciation!$B$5:$B$14,1)))/(INDEX(Depreciation!$B$5:$B$14,MATCH(C6,Depreciation!$B$5:$B$14,1)+1)-INDEX(Depreciation!$B$5:$B$14,MATCH(C6,Depreciation!$B$5:$B$14,1)))*(INDEX(Depreciation!$D$5:$D$14,MATCH(C6,Depreciation!$B$5:$B$14,1)+1)-INDEX(Depreciation!$D$5:$D$14,MATCH(C6,Depreciation!$B$5:$B$14,1))),INDEX(Depreciation!$D$5:$D$14,MATCH(C6,Depreciation!$B$5:$B$14,1))) -> 0.21228571 | I6: =IFERROR(MIN(D6,D6*H6/G6),0) -> 6663.2174 | J6: =D6-I6 -> 19336.783 | K6: =IFERROR(J6/E6,0) -> 0.13811988 | L6: =MAX(0,MIN(C6,100000)-B6) -> 60000 | M6: =MAX(0,MIN(C6,150000)-MAX(B6,100000)) -> 50000 | N6: =MAX(0,C6-MAX(B6,150000)) -> 30000 | O6: =IFERROR((L6*Inputs!$C$23+M6*Inputs!$C$24+N6*Inputs!$C$25)/E6,0) -> 0.055714286 | P6: =IFERROR(Inputs!$C$13/24,0) -> 0.14791667 | Q6: =IFERROR(Inputs!$C$15/Inputs!$C$17,0) -> 0.016363636 | R6: =Inputs!$C$18 -> 0.08 | S6: =IFERROR((Inputs!$C$19+Inputs!$C$20)/Inputs!$C$5,0) -> 0.037272727 | T6: =IFERROR(D6*Inputs!$C$46/E6,0) -> 0.013 | U6: =IFERROR(IF(Inputs!$C$32="Cash",(D6+I6)/2*Inputs!$C$33*F6,(D6*(1-Inputs!$C$35)*Inputs!$C$36*Inputs!$C$34*F6+D6*Inputs!$C$35*Inputs!$C$33*F6))/E6,0) -> 0.013362225 | V6: =K6+O6+P6+Q6+R6+S6+T6+U6 -> 0.50174942 | W6: =V6*Inputs!$C$5 -> 27596.218
A7: C — Buy 70k, sell 180k (24 mo) | B7: 70000 | C7: 180000 | D7: 19000 | E7: =C7-B7 -> 110000 | F7: =IFERROR(E7/Inputs!$C$5,0) -> 2 | G7: =IFERROR(INDEX(Depreciation!$D$5:$D$14,MATCH(B7,Depreciation!$B$5:$B$14,1))+(B7-INDEX(Depreciation!$B$5:$B$14,MATCH(B7,Depreciation!$B$5:$B$14,1)))/(INDEX(Depreciation!$B$5:$B$14,MATCH(B7,Depreciation!$B$5:$B$14,1)+1)-INDEX(Depreciation!$B$5:$B$14,MATCH(B7,Depreciation!$B$5:$B$14,1)))*(INDEX(Depreciation!$D$5:$D$14,MATCH(B7,Depreciation!$B$5:$B$14,1)+1)-INDEX(Depreciation!$D$5:$D$14,MATCH(B7,Depreciation!$B$5:$B$14,1))),INDEX(Depreciation!$D$5:$D$14,MATCH(B7,Depreciation!$B$5:$B$14,1))) -> 0.58274286 | H7: =IFERROR(INDEX(Depreciation!$D$5:$D$14,MATCH(C7,Depreciation!$B$5:$B$14,1))+(C7-INDEX(Depreciation!$B$5:$B$14,MATCH(C7,Depreciation!$B$5:$B$14,1)))/(INDEX(Depreciation!$B$5:$B$14,MATCH(C7,Depreciation!$B$5:$B$14,1)+1)-INDEX(Depreciation!$B$5:$B$14,MATCH(C7,Depreciation!$B$5:$B$14,1)))*(INDEX(Depreciation!$D$5:$D$14,MATCH(C7,Depreciation!$B$5:$B$14,1)+1)-INDEX(Depreciation!$D$5:$D$14,MATCH(C7,Depreciation!$B$5:$B$14,1))),INDEX(Depreciation!$D$5:$D$14,MATCH(C7,Depreciation!$B$5:$B$14,1))) -> 0.21228571 | I7: =IFERROR(MIN(D7,D7*H7/G7),0) -> 6921.4552 | J7: =D7-I7 -> 12078.545 | K7: =IFERROR(J7/E7,0) -> 0.10980495 | L7: =MAX(0,MIN(C7,100000)-B7) -> 30000 | M7: =MAX(0,MIN(C7,150000)-MAX(B7,100000)) -> 50000 | N7: =MAX(0,C7-MAX(B7,150000)) -> 30000 | O7: =IFERROR((L7*Inputs!$C$23+M7*Inputs!$C$24+N7*Inputs!$C$25)/E7,0) -> 0.062727273 | P7: =IFERROR(Inputs!$C$13/24,0) -> 0.14791667 | Q7: =IFERROR(Inputs!$C$15/Inputs!$C$17,0) -> 0.016363636 | R7: =Inputs!$C$18 -> 0.08 | S7: =IFERROR((Inputs!$C$19+Inputs!$C$20)/Inputs!$C$5,0) -> 0.037272727 | T7: =IFERROR(D7*Inputs!$C$46/E7,0) -> 0.012090909 | U7: =IFERROR(IF(Inputs!$C$32="Cash",(D7+I7)/2*Inputs!$C$33*F7,(D7*(1-Inputs!$C$35)*Inputs!$C$36*Inputs!$C$34*F7+D7*Inputs!$C$35*Inputs!$C$33*F7))/E7,0) -> 0.010604232 | V7: =K7+O7+P7+Q7+R7+S7+T7+U7 -> 0.4767804 | W7: =V7*Inputs!$C$5 -> 26222.922
A8: D — Buy 100k, run to 210k (24 mo) | B8: 100000 | C8: 210000 | D8: 11000 | E8: =C8-B8 -> 110000 | F8: =IFERROR(E8/Inputs!$C$5,0) -> 2 | G8: =IFERROR(INDEX(Depreciation!$D$5:$D$14,MATCH(B8,Depreciation!$B$5:$B$14,1))+(B8-INDEX(Depreciation!$B$5:$B$14,MATCH(B8,Depreciation!$B$5:$B$14,1)))/(INDEX(Depreciation!$B$5:$B$14,MATCH(B8,Depreciation!$B$5:$B$14,1)+1)-INDEX(Depreciation!$B$5:$B$14,MATCH(B8,Depreciation!$B$5:$B$14,1)))*(INDEX(Depreciation!$D$5:$D$14,MATCH(B8,Depreciation!$B$5:$B$14,1)+1)-INDEX(Depreciation!$D$5:$D$14,MATCH(B8,Depreciation!$B$5:$B$14,1))),INDEX(Depreciation!$D$5:$D$14,MATCH(B8,Depreciation!$B$5:$B$14,1))) -> 0.41428571 | H8: =IFERROR(INDEX(Depreciation!$D$5:$D$14,MATCH(C8,Depreciation!$B$5:$B$14,1))+(C8-INDEX(Depreciation!$B$5:$B$14,MATCH(C8,Depreciation!$B$5:$B$14,1)))/(INDEX(Depreciation!$B$5:$B$14,MATCH(C8,Depreciation!$B$5:$B$14,1)+1)-INDEX(Depreciation!$B$5:$B$14,MATCH(C8,Depreciation!$B$5:$B$14,1)))*(INDEX(Depreciation!$D$5:$D$14,MATCH(C8,Depreciation!$B$5:$B$14,1)+1)-INDEX(Depreciation!$D$5:$D$14,MATCH(C8,Depreciation!$B$5:$B$14,1))),INDEX(Depreciation!$D$5:$D$14,MATCH(C8,Depreciation!$B$5:$B$14,1))) -> 0.17314286 | I8: =IFERROR(MIN(D8,D8*H8/G8),0) -> 4597.2414 | J8: =D8-I8 -> 6402.7586 | K8: =IFERROR(J8/E8,0) -> 0.058206897 | L8: =MAX(0,MIN(C8,100000)-B8) -> 0 | M8: =MAX(0,MIN(C8,150000)-MAX(B8,100000)) -> 50000 | N8: =MAX(0,C8-MAX(B8,150000)) -> 60000 | O8: =IFERROR((L8*Inputs!$C$23+M8*Inputs!$C$24+N8*Inputs!$C$25)/E8,0) -> 0.081818182 | P8: =IFERROR(Inputs!$C$13/24,0) -> 0.14791667 | Q8: =IFERROR(Inputs!$C$15/Inputs!$C$17,0) -> 0.016363636 | R8: =Inputs!$C$18 -> 0.08 | S8: =IFERROR((Inputs!$C$19+Inputs!$C$20)/Inputs!$C$5,0) -> 0.037272727 | T8: =IFERROR(D8*Inputs!$C$46/E8,0) -> 0.007 | U8: =IFERROR(IF(Inputs!$C$32="Cash",(D8+I8)/2*Inputs!$C$33*F8,(D8*(1-Inputs!$C$35)*Inputs!$C$36*Inputs!$C$34*F8+D8*Inputs!$C$35*Inputs!$C$33*F8))/E8,0) -> 0.0063806897 | V8: =K8+O8+P8+Q8+R8+S8+T8+U8 -> 0.4349588 | W8: =V8*Inputs!$C$5 -> 23922.734
A9: E — Buy new/CPO 5k, run to 200k | B9: 5000 | C9: 200000 | D9: 42000 | E9: =C9-B9 -> 195000 | F9: =IFERROR(E9/Inputs!$C$5,0) -> 3.5454545 | G9: =IFERROR(INDEX(Depreciation!$D$5:$D$14,MATCH(B9,Depreciation!$B$5:$B$14,1))+(B9-INDEX(Depreciation!$B$5:$B$14,MATCH(B9,Depreciation!$B$5:$B$14,1)))/(INDEX(Depreciation!$B$5:$B$14,MATCH(B9,Depreciation!$B$5:$B$14,1)+1)-INDEX(Depreciation!$B$5:$B$14,MATCH(B9,Depreciation!$B$5:$B$14,1)))*(INDEX(Depreciation!$D$5:$D$14,MATCH(B9,Depreciation!$B$5:$B$14,1)+1)-INDEX(Depreciation!$D$5:$D$14,MATCH(B9,Depreciation!$B$5:$B$14,1))),INDEX(Depreciation!$D$5:$D$14,MATCH(B9,Depreciation!$B$5:$B$14,1))) -> 0.98428571 | H9: =IFERROR(INDEX(Depreciation!$D$5:$D$14,MATCH(C9,Depreciation!$B$5:$B$14,1))+(C9-INDEX(Depreciation!$B$5:$B$14,MATCH(C9,Depreciation!$B$5:$B$14,1)))/(INDEX(Depreciation!$B$5:$B$14,MATCH(C9,Depreciation!$B$5:$B$14,1)+1)-INDEX(Depreciation!$B$5:$B$14,MATCH(C9,Depreciation!$B$5:$B$14,1)))*(INDEX(Depreciation!$D$5:$D$14,MATCH(C9,Depreciation!$B$5:$B$14,1)+1)-INDEX(Depreciation!$D$5:$D$14,MATCH(C9,Depreciation!$B$5:$B$14,1))),INDEX(Depreciation!$D$5:$D$14,MATCH(C9,Depreciation!$B$5:$B$14,1))) -> 0.18428571 | I9: =IFERROR(MIN(D9,D9*H9/G9),0) -> 7863.5704 | J9: =D9-I9 -> 34136.43 | K9: =IFERROR(J9/E9,0) -> 0.17505861 | L9: =MAX(0,MIN(C9,100000)-B9) -> 95000 | M9: =MAX(0,MIN(C9,150000)-MAX(B9,100000)) -> 50000 | N9: =MAX(0,C9-MAX(B9,150000)) -> 50000 | O9: =IFERROR((L9*Inputs!$C$23+M9*Inputs!$C$24+N9*Inputs!$C$25)/E9,0) -> 0.055641026 | P9: =IFERROR(Inputs!$C$13/24,0) -> 0.14791667 | Q9: =IFERROR(Inputs!$C$15/Inputs!$C$17,0) -> 0.016363636 | R9: =Inputs!$C$18 -> 0.08 | S9: =IFERROR((Inputs!$C$19+Inputs!$C$20)/Inputs!$C$5,0) -> 0.037272727 | T9: =IFERROR(D9*Inputs!$C$46/E9,0) -> 0.015076923 | U9: =IFERROR(IF(Inputs!$C$32="Cash",(D9+I9)/2*Inputs!$C$33*F9,(D9*(1-Inputs!$C$35)*Inputs!$C$36*Inputs!$C$34*F9+D9*Inputs!$C$35*Inputs!$C$33*F9))/E9,0) -> 0.020398733 | V9: =K9+O9+P9+Q9+R9+S9+T9+U9 -> 0.54772833 | W9: =V9*Inputs!$C$5 -> 30125.058
A10: Assumes a 24 mpg mid-size SUV and crossover tires for all strategies so the comparison isolates buy/sell timing rather than vehicle choice.
A12: LEASE — why it's excluded
A13: Typical lease mileage cap (mi/yr) | C13: 12000
A14: Annual miles driven | C14: =Inputs!$C$5 -> 55000
A15: Overage miles per year | C15: =MAX(0,C14-C13) -> 43000
A16: Overage charge ($/mi, low end) | C16: 0.15
A17: Overage charge ($/mi, high end) | C17: 0.3
A18: Annual overage penalty — low | C18: =C15*C16 -> 6450
A19: Annual overage penalty — high | C19: =C15*C17 -> 12900
A20: Overage alone runs $6,000-$13,500 a year before a single lease payment. Not a close call.
A22: • Depreciation per mile keeps falling as you buy higher on the odometer — Strategy D is less than half of Strategy B. What kills D is repair variance and downtime, which the reserve rates only partly capture. For a driver whose income depends on being somewhere, a tow is a repair bill plus an unbillable day.
A23: • 180,000 is not the depreciation-optimal exit. The curve is flattest past 150k, so pure depreciation math says hold longer. Repair variance is what argues for getting out. On a Toyota with credible 250k legs, stretching toward 200k genuinely does lower cost per mile — you're accepting a wider distribution to get there.
A24: • Strategy E is worst because you personally absorb the first-year cliff (KBB puts it near 20%) that Strategies A-D let someone else eat.
A25: • Two-cheap-vehicles-in-rotation isn't modeled because its economics hinge almost entirely on whether the owner does his own brakes and suspension. If he does, it becomes competitive; if not, doubled failure exposure sinks it.

Sheet HoldPeriod
A1: Hold-Period Resale Analysis
A2: How much the vehicle is worth, and what depreciation costs per mile, at each length of ownership. Driven by the buy odometer and annual miles on the Inputs tab.
A3: At 55,000 mi/yr a 2-year hold means selling at 150,000 miles. A 3-year hold means 205,000.
A5: Model | B5: Category | C5: Tier | D5: Purchase price | E5: Resale mult. | F5: 1yr sell odo | G5: 1yr resale | H5: 1yr deprec $/mi | I5: 2yr sell odo | J5: 2yr resale | K5: 2yr deprec $/mi | L5: 2.5yr sell odo | M5: 2.5yr resale | N5: 2.5yr deprec $/mi | O5: 3yr sell odo | P5: 3yr resale | Q5: 3yr deprec $/mi | R5: 4yr sell odo | S5: 4yr resale | T5: 4yr deprec $/mi
A6: Chevrolet Tahoe | B6: Full-size BOF SUV | C6: T1 | D6: =Models!G7 -> 46000 | E6: =Models!F7 -> 0.93986254 | F6: =Depreciation!$C$32 -> 95000 | G6: =MIN($D6,$D6*Depreciation!$E$32*$E6) -> 22963.417 | H6: =IFERROR(($D6-G6)/(1*Inputs!$C$5),0) -> 0.41884696 | I6: =Depreciation!$C$33 -> 150000 | J6: =MIN($D6,$D6*Depreciation!$E$33*$E6) -> 13271.928 | K6: =IFERROR(($D6-J6)/(2*Inputs!$C$5),0) -> 0.29752793 | L6: =Depreciation!$C$34 -> 177500 | M6: =MIN($D6,$D6*Depreciation!$E$34*$E6) -> 11262.498 | N6: =IFERROR(($D6-M6)/(2.5*Inputs!$C$5),0) -> 0.25263638 | O6: =Depreciation!$C$35 -> 205000 | P6: =MIN($D6,$D6*Depreciation!$E$35*$E6) -> 9327.63 | Q6: =IFERROR(($D6-P6)/(3*Inputs!$C$5),0) -> 0.22225679 | R6: =Depreciation!$C$36 -> 260000 | S6: =MIN($D6,$D6*Depreciation!$E$36*$E6) -> 6710.5252 | T6: =IFERROR(($D6-S6)/(4*Inputs!$C$5),0) -> 0.17858852
A7: Chevrolet Tahoe 3.0L Duramax | B7: Full-size BOF SUV | C7: T1 | D7: =Models!G8 -> 48000 | E7: =Models!F8 -> 0.93986254 | F7: =Depreciation!$C$32 -> 95000 | G7: =MIN($D7,$D7*Depreciation!$E$32*$E7) -> 23961.827 | H7: =IFERROR(($D7-G7)/(1*Inputs!$C$5),0) -> 0.4370577 | I7: =Depreciation!$C$33 -> 150000 | J7: =MIN($D7,$D7*Depreciation!$E$33*$E7) -> 13848.968 | K7: =IFERROR(($D7-J7)/(2*Inputs!$C$5),0) -> 0.31046393 | L7: =Depreciation!$C$34 -> 177500 | M7: =MIN($D7,$D7*Depreciation!$E$34*$E7) -> 11752.172 | N7: =IFERROR(($D7-M7)/(2.5*Inputs!$C$5),0) -> 0.26362057 | O7: =Depreciation!$C$35 -> 205000 | P7: =MIN($D7,$D7*Depreciation!$E$35*$E7) -> 9733.1791 | Q7: =IFERROR(($D7-P7)/(3*Inputs!$C$5),0) -> 0.23192013 | R7: =Depreciation!$C$36 -> 260000 | S7: =MIN($D7,$D7*Depreciation!$E$36*$E7) -> 7002.2872 | T7: =IFERROR(($D7-S7)/(4*Inputs!$C$5),0) -> 0.18635324
A8: Chevrolet Suburban | B8: Full-size BOF SUV | C8: T1 | D8: =Models!G9 -> 45000 | E8: =Models!F9 -> 0.7628866 | F8: =Depreciation!$C$32 -> 95000 | G8: =MIN($D8,$D8*Depreciation!$E$32*$E8) -> 18234.205 | H8: =IFERROR(($D8-G8)/(1*Inputs!$C$5),0) -> 0.48665081 | I8: =Depreciation!$C$33 -> 150000 | J8: =MIN($D8,$D8*Depreciation!$E$33*$E8) -> 10538.634 | K8: =IFERROR(($D8-J8)/(2*Inputs!$C$5),0) -> 0.31328514 | L8: =Depreciation!$C$34 -> 177500 | M8: =MIN($D8,$D8*Depreciation!$E$34*$E8) -> 8943.0376 | N8: =IFERROR(($D8-M8)/(2.5*Inputs!$C$5),0) -> 0.26223245 | O8: =Depreciation!$C$35 -> 205000 | P8: =MIN($D8,$D8*Depreciation!$E$35*$E8) -> 7406.6468 | Q8: =IFERROR(($D8-P8)/(3*Inputs!$C$5),0) -> 0.2278385 | R8: =Depreciation!$C$36 -> 260000 | S8: =MIN($D8,$D8*Depreciation!$E$36*$E8) -> 5328.5229 | T8: =IFERROR(($D8-S8)/(4*Inputs!$C$5),0) -> 0.1803249
A9: GMC Yukon | B9: Full-size BOF SUV | C9: T1 | D9: =Models!G10 -> 49000 | E9: =Models!F10 -> 0.89347079 | F9: =Depreciation!$C$32 -> 95000 | G9: =MIN($D9,$D9*Depreciation!$E$32*$E9) -> 23253.631 | H9: =IFERROR(($D9-G9)/(1*Inputs!$C$5),0) -> 0.46811579 | I9: =Depreciation!$C$33 -> 150000 | J9: =MIN($D9,$D9*Depreciation!$E$33*$E9) -> 13439.66 | K9: =IFERROR(($D9-J9)/(2*Inputs!$C$5),0) -> 0.32327582 | L9: =Depreciation!$C$34 -> 177500 | M9: =MIN($D9,$D9*Depreciation!$E$34*$E9) -> 11404.835 | N9: =IFERROR(($D9-M9)/(2.5*Inputs!$C$5),0) -> 0.27341938 | O9: =Depreciation!$C$35 -> 205000 | P9: =MIN($D9,$D9*Depreciation!$E$35*$E9) -> 9445.5136 | Q9: =IFERROR(($D9-P9)/(3*Inputs!$C$5),0) -> 0.23972416 | R9: =Depreciation!$C$36 -> 260000 | S9: =MIN($D9,$D9*Depreciation!$E$36*$E9) -> 6795.3335 | T9: =IFERROR(($D9-S9)/(4*Inputs!$C$5),0) -> 0.19183939
A10: GMC Yukon XL | B10: Full-size BOF SUV | C10: T1 | D10: =Models!G11 -> 50000 | E10: =Models!F11 -> 0.89347079 | F10: =Depreciation!$C$32 -> 95000 | G10: =MIN($D10,$D10*Depreciation!$E$32*$E10) -> 23728.195 | H10: =IFERROR(($D10-G10)/(1*Inputs!$C$5),0) -> 0.47766918 | I10: =Depreciation!$C$33 -> 150000 | J10: =MIN($D10,$D10*Depreciation!$E$33*$E10) -> 13713.938 | K10: =IFERROR(($D10-J10)/(2*Inputs!$C$5),0) -> 0.32987329 | L10: =Depreciation!$C$34 -> 177500 | M10: =MIN($D10,$D10*Depreciation!$E$34*$E10) -> 11637.586 | N10: =IFERROR(($D10-M10)/(2.5*Inputs!$C$5),0) -> 0.27899937 | O10: =Depreciation!$C$35 -> 205000 | P10: =MIN($D10,$D10*Depreciation!$E$35*$E10) -> 9638.2792 | Q10: =IFERROR(($D10-P10)/(3*Inputs!$C$5),0) -> 0.24461649 | R10: =Depreciation!$C$36 -> 260000 | S10: =MIN($D10,$D10*Depreciation!$E$36*$E10) -> 6934.0138 | T10: =IFERROR(($D10-S10)/(4*Inputs!$C$5),0) -> 0.19575448
A11: Ford Expedition | B11: Full-size BOF SUV | C11: T2 | D11: =Models!G12 -> 43000 | E11: =Models!F12 -> 0.68728522 | F11: =Depreciation!$C$32 -> 95000 | G11: =MIN($D11,$D11*Depreciation!$E$32*$E11) -> 15697.114 | H11: =IFERROR(($D11-G11)/(1*Inputs!$C$5),0) -> 0.49641611 | I11: =Depreciation!$C$33 -> 150000 | J11: =MIN($D11,$D11*Depreciation!$E$33*$E11) -> 9072.2977 | K11: =IFERROR(($D11-J11)/(2*Inputs!$C$5),0) -> 0.30843366 | L11: =Depreciation!$C$34 -> 177500 | M11: =MIN($D11,$D11*Depreciation!$E$34*$E11) -> 7698.7111 | N11: =IFERROR(($D11-M11)/(2.5*Inputs!$C$5),0) -> 0.25673665 | O11: =Depreciation!$C$35 -> 205000 | P11: =MIN($D11,$D11*Depreciation!$E$35*$E11) -> 6376.0924 | Q11: =IFERROR(($D11-P11)/(3*Inputs!$C$5),0) -> 0.22196308 | R11: =Depreciation!$C$36 -> 260000 | S11: =MIN($D11,$D11*Depreciation!$E$36*$E11) -> 4587.1168 | T11: =IFERROR(($D11-S11)/(4*Inputs!$C$5),0) -> 0.17460401
A12: Toyota Sequoia (pre-2023 5.7 V8) | B12: Full-size BOF SUV | C12: T1 | D12: =Models!G13 -> 46000 | E12: =Models!F13 -> 0.99656357 | F12: =Depreciation!$C$32 -> 95000 | G12: =MIN($D12,$D12*Depreciation!$E$32*$E12) -> 24348.779 | H12: =IFERROR(($D12-G12)/(1*Inputs!$C$5),0) -> 0.39365857 | I12: =Depreciation!$C$33 -> 150000 | J12: =MIN($D12,$D12*Depreciation!$E$33*$E12) -> 14072.611 | K12: =IFERROR(($D12-J12)/(2*Inputs!$C$5),0) -> 0.29024899 | L12: =Depreciation!$C$34 -> 177500 | M12: =MIN($D12,$D12*Depreciation!$E$34*$E12) -> 11941.954 | N12: =IFERROR(($D12-M12)/(2.5*Inputs!$C$5),0) -> 0.24769488 | O12: =Depreciation!$C$35 -> 205000 | P12: =MIN($D12,$D12*Depreciation!$E$35*$E12) -> 9890.3572 | Q12: =IFERROR(($D12-P12)/(3*Inputs!$C$5),0) -> 0.21884632 | R12: =Depreciation!$C$36 -> 260000 | S12: =MIN($D12,$D12*Depreciation!$E$36*$E12) -> 7115.3649 | T12: =IFERROR(($D12-S12)/(4*Inputs!$C$5),0) -> 0.17674834
A13: Nissan Armada | B13: Full-size BOF SUV | C13: T2 | D13: =Models!G14 -> 32000 | E13: =Models!F14 -> 0.68728522 | F13: =Depreciation!$C$32 -> 95000 | G13: =MIN($D13,$D13*Depreciation!$E$32*$E13) -> 11681.573 | H13: =IFERROR(($D13-G13)/(1*Inputs!$C$5),0) -> 0.36942595 | I13: =Depreciation!$C$33 -> 150000 | J13: =MIN($D13,$D13*Depreciation!$E$33*$E13) -> 6751.4774 | K13: =IFERROR(($D13-J13)/(2*Inputs!$C$5),0) -> 0.22953202 | L13: =Depreciation!$C$34 -> 177500 | M13: =MIN($D13,$D13*Depreciation!$E$34*$E13) -> 5729.2733 | N13: =IFERROR(($D13-M13)/(2.5*Inputs!$C$5),0) -> 0.19105983 | O13: =Depreciation!$C$35 -> 205000 | P13: =MIN($D13,$D13*Depreciation!$E$35*$E13) -> 4744.999 | Q13: =IFERROR(($D13-P13)/(3*Inputs!$C$5),0) -> 0.16518182 | R13: =Depreciation!$C$36 -> 260000 | S13: =MIN($D13,$D13*Depreciation!$E$36*$E13) -> 3413.6683 | T13: =IFERROR(($D13-S13)/(4*Inputs!$C$5),0) -> 0.12993787
A14: Cadillac Escalade | B14: Full-size BOF SUV | C14: T3 | D14: =Models!G15 -> 70000 | E14: =Models!F15 -> 0.65635739 | F14: =Depreciation!$C$32 -> 95000 | G14: =MIN($D14,$D14*Depreciation!$E$32*$E14) -> 24403.536 | H14: =IFERROR(($D14-G14)/(1*Inputs!$C$5),0) -> 0.82902662 | I14: =Depreciation!$C$33 -> 150000 | J14: =MIN($D14,$D14*Depreciation!$E$33*$E14) -> 14104.258 | K14: =IFERROR(($D14-J14)/(2*Inputs!$C$5),0) -> 0.50814311 | L14: =Depreciation!$C$34 -> 177500 | M14: =MIN($D14,$D14*Depreciation!$E$34*$E14) -> 11968.81 | N14: =IFERROR(($D14-M14)/(2.5*Inputs!$C$5),0) -> 0.42204502 | O14: =Depreciation!$C$35 -> 205000 | P14: =MIN($D14,$D14*Depreciation!$E$35*$E14) -> 9912.5994 | Q14: =IFERROR(($D14-P14)/(3*Inputs!$C$5),0) -> 0.36416606 | R14: =Depreciation!$C$36 -> 260000 | S14: =MIN($D14,$D14*Depreciation!$E$36*$E14) -> 7131.3665 | T14: =IFERROR(($D14-S14)/(4*Inputs!$C$5),0) -> 0.28576652
A15: Jeep Grand Wagoneer | B15: Full-size BOF SUV | C15: T3 | D15: =Models!G16 -> 54000 | E15: =Models!F16 -> 0.75601375 | F15: =Depreciation!$C$32 -> 95000 | G15: =MIN($D15,$D15*Depreciation!$E$32*$E15) -> 21683.92 | H15: =IFERROR(($D15-G15)/(1*Inputs!$C$5),0) -> 0.58756509 | I15: =Depreciation!$C$33 -> 150000 | J15: =MIN($D15,$D15*Depreciation!$E$33*$E15) -> 12532.43 | K15: =IFERROR(($D15-J15)/(2*Inputs!$C$5),0) -> 0.37697791 | L15: =Depreciation!$C$34 -> 177500 | M15: =MIN($D15,$D15*Depreciation!$E$34*$E15) -> 10634.964 | N15: =IFERROR(($D15-M15)/(2.5*Inputs!$C$5),0) -> 0.31538208 | O15: =Depreciation!$C$35 -> 205000 | P15: =MIN($D15,$D15*Depreciation!$E$35*$E15) -> 8807.9043 | Q15: =IFERROR(($D15-P15)/(3*Inputs!$C$5),0) -> 0.27389149 | R15: =Depreciation!$C$36 -> 260000 | S15: =MIN($D15,$D15*Depreciation!$E$36*$E15) -> 6336.6218 | T15: =IFERROR(($D15-S15)/(4*Inputs!$C$5),0) -> 0.21665172
A16: Jeep Grand Cherokee | B16: Mid-size SUV | C16: T2 | D16: =Models!G17 -> 32000 | E16: =Models!F17 -> 0.8419244 | F16: =Depreciation!$C$32 -> 95000 | G16: =MIN($D16,$D16*Depreciation!$E$32*$E16) -> 14309.927 | H16: =IFERROR(($D16-G16)/(1*Inputs!$C$5),0) -> 0.32163769 | I16: =Depreciation!$C$33 -> 150000 | J16: =MIN($D16,$D16*Depreciation!$E$33*$E16) -> 8270.5598 | K16: =IFERROR(($D16-J16)/(2*Inputs!$C$5),0) -> 0.21572218 | L16: =Depreciation!$C$34 -> 177500 | M16: =MIN($D16,$D16*Depreciation!$E$34*$E16) -> 7018.3598 | N16: =IFERROR(($D16-M16)/(2.5*Inputs!$C$5),0) -> 0.18168466 | O16: =Depreciation!$C$35 -> 205000 | P16: =MIN($D16,$D16*Depreciation!$E$35*$E16) -> 5812.6237 | Q16: =IFERROR(($D16-P16)/(3*Inputs!$C$5),0) -> 0.15871137 | R16: =Depreciation!$C$36 -> 260000 | S16: =MIN($D16,$D16*Depreciation!$E$36*$E16) -> 4181.7437 | T16: =IFERROR(($D16-S16)/(4*Inputs!$C$5),0) -> 0.12644662
A17: Jeep Grand Cherokee L | B17: 3-row crossover | C17: T2 | D17: =Models!G18 -> 38000 | E17: =Models!F18 -> 0.8419244 | F17: =Depreciation!$C$32 -> 95000 | G17: =MIN($D17,$D17*Depreciation!$E$32*$E17) -> 16993.038 | H17: =IFERROR(($D17-G17)/(1*Inputs!$C$5),0) -> 0.38194476 | I17: =Depreciation!$C$33 -> 150000 | J17: =MIN($D17,$D17*Depreciation!$E$33*$E17) -> 9821.2897 | K17: =IFERROR(($D17-J17)/(2*Inputs!$C$5),0) -> 0.25617009 | L17: =Depreciation!$C$34 -> 177500 | M17: =MIN($D17,$D17*Depreciation!$E$34*$E17) -> 8334.3023 | N17: =IFERROR(($D17-M17)/(2.5*Inputs!$C$5),0) -> 0.21575053 | O17: =Depreciation!$C$35 -> 205000 | P17: =MIN($D17,$D17*Depreciation!$E$35*$E17) -> 6902.4907 | Q17: =IFERROR(($D17-P17)/(3*Inputs!$C$5),0) -> 0.18846975 | R17: =Depreciation!$C$36 -> 260000 | S17: =MIN($D17,$D17*Depreciation!$E$36*$E17) -> 4965.8206 | T17: =IFERROR(($D17-S17)/(4*Inputs!$C$5),0) -> 0.15015536
... A81: Ram 2500 (Cummins) | B81: Heavy-duty truck | C81: T2 | D81: =Models!G82 -> 52000 | E81: =Models!F82 -> 1.0309278 | F81: =Depreciation!$C$32 -> 95000 | G81: =MIN($D81,$D81*Depreciation!$E$32*$E81) -> 28473.834 | H81: =IFERROR(($D81-G81)/(1*Inputs!$C$5),0) -> 0.42774847 | I81: =Depreciation!$C$33 -> 150000 | J81: =MIN($D81,$D81*Depreciation!$E$33*$E81) -> 16456.726 | K81: =IFERROR(($D81-J81)/(2*Inputs!$C$5),0) -> 0.32312067 | L81: =Depreciation!$C$34 -> 177500 | M81: =MIN($D81,$D81*Depreciation!$E$34*$E81) -> 13965.104 | N81: =IFERROR(($D81-M81)/(2.5*Inputs!$C$5),0) -> 0.27661743 | O81: =Depreciation!$C$35 -> 205000 | P81: =MIN($D81,$D81*Depreciation!$E$35*$E81) -> 11565.935 | Q81: =IFERROR(($D81-P81)/(3*Inputs!$C$5),0) -> 0.24505494 | R81: =Depreciation!$C$36 -> 260000 | S81: =MIN($D81,$D81*Depreciation!$E$36*$E81) -> 8320.8165 | T81: =IFERROR(($D81-S81)/(4*Inputs!$C$5),0) -> 0.19854174
A83: - Depreciation per mile FALLS the longer you hold, because the depreciation curve flattens past 100,000 miles. That is the whole argument for a longer hold and it is visible in these columns.
A84: - It is not the whole story. Repair risk climbs in the opposite direction, and the repair reserve on the Inputs tab (3 cents/mi under 100k, 6 cents 100-150k, 10 cents over 150k) is what pulls the total back the other way. Read this tab alongside the Strategies tab, not instead of it.
A85: - A 2-year hold at 55,000 mi/yr sells the vehicle at 150,000 miles - still inside most manufacturers' credible service life. A 4-year hold sells at 260,000, which is past the point where the resale curve has data behind it. Treat the 4-year column as directional only.
A86: - Resale is purchase price x market retention ratio x the model's resale-strength factor, capped at purchase price. It does not model condition, accident history, or a soft used market.

Sheet Tax
B1: Ownership Structure & Tax Scenarios
B2: Personal ownership with the standard mileage rate vs. business ownership with accelerated depreciation.
B4: SCENARIO SETUP
B5: Vehicle purchase price | C5: 35000 | D5: The vehicle being analyzed. Independent of the Models tab so you can test any candidate.
B6: GVWR over 6,000 lb? | C6: Yes | D6: Determines whether Sec. 280F luxury-auto caps apply. Check the door-jamb sticker — it is the only authoritative source.
B7: Employment type | C7: =Inputs!$C$39 -> Self-employed | D7: Set on the Inputs tab.
B8: Annual miles | C8: =Inputs!$C$5 -> 55000
B9: Business use % | C9: =Inputs!$C$40 -> 0.9
B10: Business miles per year | C10: =C8*C9 -> 49500
B11: Years per cycle | C11: =Inputs!$C$9 -> 2.5454545
B12: Combined deduction benefit rate | C12: =Inputs!$C$45 -> 0.4118 | D12: Federal + SE + Indiana. Zero if W-2.
B13: Estimated resale at end of cycle | C13: =C5*Depreciation!$C$23 -> 8969.7158 | D13: Uses the market retention ratio. Drives the recapture calculation below.
B14: Annual actual operating cost (deductible portion) | C14: =(Inputs!$C$19+Inputs!$C$20)+C8*(Inputs!$C$13/24+Inputs!$C$15/Inputs!$C$17+Inputs!$C$18+Inputs!$C$29) -> 18549.702 | D14: Fuel, tires, maintenance, repair reserve, insurance, registration. Excludes depreciation, which is handled per scenario.
B16: SCENARIO 1 — Personal ownership, standard mileage, W-2 employee
B17: Annual deduction | C17: 0 | D17: Zero. TCJA suspended unreimbursed employee business expenses; OBBBA (7/4/2025) made it permanent via IRC 67(g). IRS Pub 463 confirms.
B18: Annual tax benefit | C18: 0 | D18: There is no deduction to benefit from.
B19: Verdict | C19: =IF(Inputs!$C$39="W-2","THIS IS YOUR SITUATION - confirm with a CPA","Not applicable") -> Not applicable | D19: If the driver is a W-2 employee, the only tax-advantaged route is an employer accountable-plan reimbursement.
B21: SCENARIO 2 — Personal ownership, standard mileage, self-employed
B22: IRS standard mileage rate | C22: =Inputs!$C$41 -> 0.74 | D22: 2026 blended: 72.5c Jan-Jun, 76c Jul-Dec.
B23: Annual deduction | C23: =IF(Inputs!$C$39="Self-employed",C10*C22,0) -> 36630
B24: Annual tax benefit | C24: =C23*C12 -> 15084.234
B25: Benefit per mile driven | C25: =IFERROR(C24/C8,0) -> 0.2742588
B26: Recordkeeping burden | C26: Low | D26: Mileage log only. No receipts required for the deduction itself.
B28: SCENARIO 3 — Personal ownership, actual expense method, self-employed
B29: Annual operating cost (deductible portion) | C29: =C14*C9 -> 16694.732
B30: Annual straight-line depreciation | C30: =IFERROR((C5-C13)/C11*C9,0) -> 9203.5648 | D30: Purchase less resale, spread over the cycle, times business use.
B31: Annual deduction | C31: =IF(Inputs!$C$39="Self-employed",C29+C30,0) -> 25898.297
B32: Annual tax benefit | C32: =C31*C12 -> 10664.919
B33: Advantage vs. standard mileage | C33: =C32-C24 -> -4419.3153 | D33: Negative means standard mileage wins. At 55,000 miles it usually does — the deduction scales with miles while actual per-mile cost falls.
B34: Recordkeeping burden | C34: High | D34: Every receipt, plus a depreciation schedule.
B36: SCENARIO 4 — Business ownership, Section 179 / 100% bonus depreciation
B37: Bonus depreciation % | C37: =Inputs!$C$49 -> 1 | D37: OBBBA sec. 70301 restored 100% permanently for property placed in service after 1/19/2025.
B38: First-year deduction cap | C38: =IF(C6="Yes",C5*C9,MIN(C5*C9,Inputs!$C$51)) -> 31500 | D38: Above 6,000 lb GVWR the Sec. 280F caps do not apply, so bonus can expense the full business-use portion. At or below, the cap is $20,300 for 2026 (Rev. Proc. 2026-15).
B39: Year-one deduction | C39: =IF(Inputs!$C$39="Self-employed",C38*C37,0) -> 31500
B40: Year-one tax benefit | C40: =C39*C12 -> 12971.7 | D40: The headline number every dealer quotes at you.
B41: Operating deductions over the cycle | C41: =C14*C9*C11 -> 42495.682
B42: Tax benefit on operating deductions | C42: =C41*C12 -> 17499.722
B43: Gross benefit over the cycle | C43: =C40+C42 -> 30471.422
B45: SCENARIO 4 CONTINUED — the recapture that reverses it
B46: Depreciation claimed | C46: =C39 -> 31500
B47: Adjusted basis at sale | C47: =MAX(0,C5*C9-C46) -> 0 | D47: Business-use basis less depreciation taken. Usually zero after a 100% write-off.
B48: Sale proceeds (business-use portion) | C48: =C13*C9 -> 8072.7442
B49: Gain on sale | C49: =MAX(0,C48-C47) -> 8072.7442
B50: Sec. 1245 recapture — taxed as ORDINARY income | C50: =MIN(C46,C49) -> 8072.7442 | D50: Vehicles are Sec. 1245 property. Depreciation comes back at your marginal rate, not capital gains.
B51: Recapture tax cost | C51: =C50*C12 -> 3324.3561
B52: NET benefit over the cycle | C52: =C43-C51 -> 27147.066 | D52: What business ownership is actually worth after recapture.
B53: Scenario 2 benefit over the same cycle | C53: =C24*C11 -> 38396.232 | D53: Standard mileage, self-employed, for the identical period.
B54: Business ownership advantage | C54: =C52-C53 -> -11249.166 | D54: Negative means keep it personal and take the standard mileage rate. At this turnover cadence it usually is.
B56: THE THREE TRAPS
B57: Recapture arrives fast | D57: Selling every ~30 months means the write-off reverses almost immediately. Treat Section 179 / bonus as tax DEFERRAL, not savings. It only pays if the marginal rate is high now and expected lower later, or if a specific year needs the cash flow.
B58: No switching back | D58: Claim Section 179 or bonus (or any accelerated method) on a vehicle and the standard mileage rate is permanently unavailable for that vehicle. You are on actual expense for its entire life. IRS Pub 463.
B59: The 50% cliff | D59: Business use must exceed 50% to claim Section 179 or bonus. Fall below it in a later year and you recapture the excess depreciation. Substantiation requires a contemporaneous mileage log, not a reconstruction.
B61: None of this is tax advice. Every figure here should be confirmed with a CPA before filing.

Sheet Tracker
A1: Actual Cost Tracker
A2: Log everything. The summary block compares reality against the model so you can recalibrate the assumptions on Inputs.
A4: Date | B4: Odometer | C4: Category | D4: Vendor / description | E4: Amount | F4: Notes | H4: SUMMARY | I4: Total $ | J4: $ / mile
A5: 2026-08-15 | B5: 41250 | C5: Fuel | D5: Speedway, US-31 | E5: 62.4 | F5: EXAMPLE ROW — delete once you start logging | H5: Fuel | I5: =SUMIF($C$5:$C$504,H5,$E$5:$E$504) -> 62.4 | J5: =IFERROR(I5/$I$16,0) -> 0
H6: Tires | I6: =SUMIF($C$5:$C$504,H6,$E$5:$E$504) -> 0 | J6: =IFERROR(I6/$I$16,0) -> 0
H7: Scheduled Maintenance | I7: =SUMIF($C$5:$C$504,H7,$E$5:$E$504) -> 0 | J7: =IFERROR(I7/$I$16,0) -> 0
H8: Repair | I8: =SUMIF($C$5:$C$504,H8,$E$5:$E$504) -> 0 | J8: =IFERROR(I8/$I$16,0) -> 0
H9: Insurance | I9: =SUMIF($C$5:$C$504,H9,$E$5:$E$504) -> 0 | J9: =IFERROR(I9/$I$16,0) -> 0
H10: Registration/Tax | I10: =SUMIF($C$5:$C$504,H10,$E$5:$E$504) -> 0 | J10: =IFERROR(I10/$I$16,0) -> 0
H11: Purchase | I11: =SUMIF($C$5:$C$504,H11,$E$5:$E$504) -> 0 | J11: =IFERROR(I11/$I$16,0) -> 0
H12: Sale Proceeds | I12: =SUMIF($C$5:$C$504,H12,$E$5:$E$504) -> 0 | J12: =IFERROR(I12/$I$16,0) -> 0
H13: Other | I13: =SUMIF($C$5:$C$504,H13,$E$5:$E$504) -> 0 | J13: =IFERROR(I13/$I$16,0) -> 0
H14: Total logged spend | I14: =SUM(I5:I13) -> 62.4
H16: Miles logged (max odo - min odo) | I16: =IFERROR(MAX($B$5:$B$504)-MIN($B$5:$B$504),0) -> 0
H17: ACTUAL cost per mile | I17: =IFERROR(I14/I16,0) -> 0
H18: MODELED cost per mile (Strategy B) | I18: =Strategies!V6 -> 0.50174942
H19: Variance | I19: =I17-I18 -> -0.50174942
H21: Exclude Purchase and Sale Proceeds rows when comparing to the modeled operating figure — the model handles depreciation separately.

Sheet Scoring
A1: Multi-Objective Scoring
A2: Six axes, each normalized 0-100 where higher is better. Change the weights in row 5 and every score and rank recomputes.
A3: The axes are NOT equally trustworthy. Row 6 tags each one. Cost and Efficiency are computed or measured; Comfort starts from real decibel readings; Quality and Reliability are informed guesses.
A5: WEIGHTS -> | B5: Cost | C5: 25 | D5: Quality | E5: 15 | F5: Longevity | G5: 15 | H5: Efficiency | I5: 10 | J5: Reliability | K5: 20 | L5: Comfort | M5: 15 | N5: Total | O5: =C5+E5+G5+I5+K5+M5 -> 100
C6: computed | E6: judgment | G6: iSeeCars | I6: EPA/observed | K6: SWAG | M6: measured dB
A8: Model | B8: Category | C8: Tier | D8: Cost $/mi | E8: Cabin dB | F8: Cost | G8: Quality | H8: Longevity | I8: Efficiency | J8: Reliability | K8: Comfort | L8: Weighted score | M8: Rank | N8: Undominated?
A9: Chevrolet Tahoe | B9: Full-size BOF SUV | C9: T1 | D9: 0.674 | E9: 54.5 | F9: 46.4 | G9: 90.2 | H9: 56.8 | I9: 17.4 | J9: 45.6 | K9: 63.4 | L9: =IFERROR((F9*$C$5+G9*$E$5+H9*$G$5+I9*$I$5+J9*$K$5+K9*$M$5)/$O$5,0) -> 54.02 | M9: =RANK(L9,$L$9:$L$84,0) -> 58
A10: Chevrolet Tahoe 3.0L Duramax | B10: Full-size BOF SUV | C10: T1 | D10: 0.703 | E10: 54.5 | F10: 40.2 | G10: 87.2 | H10: 56.8 | I10: 50 | J10: 57.6 | K10: 63.4 | L10: =IFERROR((F10*$C$5+G10*$E$5+H10*$G$5+I10*$I$5+J10*$K$5+K10*$M$5)/$O$5,0) -> 57.68 | M10: =RANK(L10,$L$9:$L$84,0) -> 50
A11: Chevrolet Suburban | B11: Full-size BOF SUV | C11: T1 | D11: 0.687 | E11: 54.4 | F11: 43.8 | G11: 90.2 | H11: 67.5 | I11: 15.2 | J11: 45.6 | K11: 64.4 | L11: =IFERROR((F11*$C$5+G11*$E$5+H11*$G$5+I11*$I$5+J11*$K$5+K11*$M$5)/$O$5,0) -> 54.905 | M11: =RANK(L11,$L$9:$L$84,0) -> 57
A12: GMC Yukon | B12: Full-size BOF SUV | C12: T1 | D12: 0.702 | E12: 54.5 | F12: 40.4 | G12: 90.2 | H12: 57.1 | I12: 15.2 | J12: 29 | K12: 63.4 | L12: =IFERROR((F12*$C$5+G12*$E$5+H12*$G$5+I12*$I$5+J12*$K$5+K12*$M$5)/$O$5,0) -> 49.025 | M12: =RANK(L12,$L$9:$L$84,0) -> 66
A13: GMC Yukon XL | B13: Full-size BOF SUV | C13: T1 | D13: 0.709 | E13: 54.5 | F13: 39 | G13: 90.2 | H13: 60.7 | I13: 15.2 | J13: 29 | K13: 63.4 | L13: =IFERROR((F13*$C$5+G13*$E$5+H13*$G$5+I13*$I$5+J13*$K$5+K13*$M$5)/$O$5,0) -> 49.215 | M13: =RANK(L13,$L$9:$L$84,0) -> 65
A14: Ford Expedition | B14: Full-size BOF SUV | C14: T2 | D14: 0.684 | E14: 54.4 | F14: 44.4 | G14: 50.2 | H14: 58.1 | I14: 13 | J14: 52.7 | K14: 64.4 | L14: =IFERROR((F14*$C$5+G14*$E$5+H14*$G$5+I14*$I$5+J14*$K$5+K14*$M$5)/$O$5,0) -> 48.845 | M14: =RANK(L14,$L$9:$L$84,0) -> 67
A15: Toyota Sequoia (pre-2023 5.7 V8) | B15: Full-size BOF SUV | C15: T1 | D15: 0.717 | E15: 55.7 | F15: 37.3 | G15: 95.5 | H15: 97.4 | I15: 0 | J15: 100 | K15: 52.3 | L15: =IFERROR((F15*$C$5+G15*$E$5+H15*$G$5+I15*$I$5+J15*$K$5+K15*$M$5)/$O$5,0) -> 66.105 | M15: =RANK(L15,$L$9:$L$84,0) -> 36 | N15: Yes
A16: Nissan Armada | B16: Full-size BOF SUV | C16: T2 | D16: 0.625 | E16: 55 | F16: 57 | G16: 77.5 | H16: 49.7 | I16: 6.5 | J16: 86.4 | K16: 58.8 | L16: =IFERROR((F16*$C$5+G16*$E$5+H16*$G$5+I16*$I$5+J16*$K$5+K16*$M$5)/$O$5,0) -> 60.08 | M16: =RANK(L16,$L$9:$L$84,0) -> 48
A17: Cadillac Escalade | B17: Full-size BOF SUV | C17: T3 | D17: 0.89 | E17: 55.5 | F17: 0 | G17: 54.2 | H17: 53.7 | I17: 6.5 | J17: 44.1 | K17: 54.2 | L17: =IFERROR((F17*$C$5+G17*$E$5+H17*$G$5+I17*$I$5+J17*$K$5+K17*$M$5)/$O$5,0) -> 33.785 | M17: =RANK(L17,$L$9:$L$84,0) -> 75
A18: Jeep Grand Wagoneer | B18: Full-size BOF SUV | C18: T3 | D18: 0.776 | E18: 58 | F18: 24.5 | G18: 55.2 | H18: 45.3 | I18: 4.3 | J18: 28.4 | K18: 31 | L18: =IFERROR((F18*$C$5+G18*$E$5+H18*$G$5+I18*$I$5+J18*$K$5+K18*$M$5)/$O$5,0) -> 31.96 | M18: =RANK(L18,$L$9:$L$84,0) -> 76
A19: Jeep Grand Cherokee | B19: Mid-size SUV | C19: T2 | D19: 0.555 | E19: 55 | F19: 72.2 | G19: 79.2 | H19: 64.9 | I19: 32.6 | J19: 30.4 | K19: 64.8 | L19: =IFERROR((F19*$C$5+G19*$E$5+H19*$G$5+I19*$I$5+J19*$K$5+K19*$M$5)/$O$5,0) -> 58.725 | M19: =RANK(L19,$L$9:$L$84,0) -> 49
A20: Jeep Grand Cherokee L | B20: 3-row crossover | C20: T2 | D20: 0.598 | E20: 55 | F20: 62.9 | G20: 79.2 | H20: 64.9 | I20: 30.4 | J20: 30.4 | K20: 64.8 | L20: =IFERROR((F20*$C$5+G20*$E$5+H20*$G$5+I20*$I$5+J20*$K$5+K20*$M$5)/$O$5,0) -> 56.18 | M20: =RANK(L20,$L$9:$L$84,0) -> 53
A21: Jeep Cherokee | B21: Compact crossover | C21: T3 | D21: 0.47 | E21: 57.5 | F21: 90.5 | G21: 33.2 | H21: 27.2 | I21: 41.3 | J21: 17.4 | K21: 41.7 | L21: =IFERROR((F21*$C$5+G21*$E$5+H21*$G$5+I21*$I$5+J21*$K$5+K21*$M$5)/$O$5,0) -> 45.55 | M21: =RANK(L21,$L$9:$L$84,0) -> 71
A22: Jeep Compass | B22: Compact crossover | C22: T3 | D22: 0.446 | E22: 58.5 | F22: 95.6 | G22: 31.9 | H22: 26.2 | I22: 50 | J22: 17.4 | K22: 32.4 | L22: =IFERROR((F22*$C$5+G22*$E$5+H22*$G$5+I22*$I$5+J22*$K$5+K22*$M$5)/$O$5,0) -> 45.955 | M22: =RANK(L22,$L$9:$L$84,0) -> 70
A23: Jeep Gladiator | B23: Midsize truck | C23: T2 | D23: 0.575 | E23: 62 | F23: 67.9 | G23: 79.2 | H23: 64.9 | I23: 23.9 | J23: 42.4 | K23: 0 | L23: =IFERROR((F23*$C$5+G23*$E$5+H23*$G$5+I23*$I$5+J23*$K$5+K23*$M$5)/$O$5,0) -> 49.46 | M23: =RANK(L23,$L$9:$L$84,0) -> 64
A24: Jeep Wrangler | B24: Midsize SUV | C24: T2 | D24: 0.587 | E24: 61.5 | F24: 65.2 | G24: 79.2 | H24: 43.4 | I24: 10.9 | J24: 42.4 | K24: 0 | L24: =IFERROR((F24*$C$5+G24*$E$5+H24*$G$5+I24*$I$5+J24*$K$5+K24*$M$5)/$O$5,0) -> 44.26 | M24: =RANK(L24,$L$9:$L$84,0) -> 72
A25: Jeep Wrangler 4xe | B25: Midsize SUV (PHEV) | C25: T3 | D25: 0.601 | E25: 61 | F25: 62.3 | G25: 52.6 | H25: 43.1 | I25: 21.7 | J25: 26.4 | K25: 0 | L25: =IFERROR((F25*$C$5+G25*$E$5+H25*$G$5+I25*$I$5+J25*$K$5+K25*$M$5)/$O$5,0) -> 37.38 | M25: =RANK(L25,$L$9:$L$84,0) -> 74
A26: Ford Explorer | B26: 3-row crossover | C26: T3 | D26: 0.537 | E26: 57 | F26: 76 | G26: 33.2 | H26: 27.2 | I26: 45.7 | J26: 50.7 | K26: 46.3 | L26: =IFERROR((F26*$C$5+G26*$E$5+H26*$G$5+I26*$I$5+J26*$K$5+K26*$M$5)/$O$5,0) -> 49.715 | M26: =RANK(L26,$L$9:$L$84,0) -> 63
A27: Chevrolet Traverse | B27: 3-row crossover | C27: T2 | D27: 0.536 | E27: 54.9 | F27: 76.3 | G27: 77.5 | H27: 63.5 | I27: 41.3 | J27: 51.6 | K27: 65.7 | L27: =IFERROR((F27*$C$5+G27*$E$5+H27*$G$5+I27*$I$5+J27*$K$5+K27*$M$5)/$O$5,0) -> 64.53 | M27: =RANK(L27,$L$9:$L$84,0) -> 41
... A29: Honda Passport | B29: Mid-size crossover | C29: T1 | D29: 0.572 | E29: 58.2 | F29: 68.6 | G29: 89.2 | H29: 73.1 | I29: 23.9 | J29: 89.4 | K29: 35.2 | L29: =IFERROR((F29*$C$5+G29*$E$5+H29*$G$5+I29*$I$5+J29*$K$5+K29*$M$5)/$O$5,0) -> 67.045 | M29: =RANK(L29,$L$9:$L$84,0) -> 35
A30: Toyota Grand Highlander Hybrid | B30: 3-row crossover | C30: T1 | D30: 0.58 | E30: 51.2 | F30: 66.8 | G30: 100 | H30: 82 | I30: 71.7 | J30: 100 | K30: 100 | L30: =IFERROR((F30*$C$5+G30*$E$5+H30*$G$5+I30*$I$5+J30*$K$5+K30*$M$5)/$O$5,0) -> 86.17 | M30: =RANK(L30,$L$9:$L$84,0) -> 3 | N30: Yes
A31: Toyota Highlander (gas) | B31: 3-row crossover | C31: T1 | D31: 0.548 | E31: 52.6 | F31: 73.6 | G31: 95.5 | H31: 69.3 | I31: 56.5 | J31: 100 | K31: 87 | L31: =IFERROR((F31*$C$5+G31*$E$5+H31*$G$5+I31*$I$5+J31*$K$5+K31*$M$5)/$O$5,0) -> 81.82 | M31: =RANK(L31,$L$9:$L$84,0) -> 5
A32: Toyota Highlander Hybrid | B32: 3-row crossover | C32: T1 | D32: 0.517 | E32: 52.6 | F32: 80.2 | G32: 100 | H32: 91.6 | I32: 80.4 | J32: 100 | K32: 87 | L32: =IFERROR((F32*$C$5+G32*$E$5+H32*$G$5+I32*$I$5+J32*$K$5+K32*$M$5)/$O$5,0) -> 89.88 | M32: =RANK(L32,$L$9:$L$84,0) -> 1 | N32: Yes
A33: Kia Telluride | B33: 3-row crossover | C33: T2 | D33: 0.556 | E33: 53.9 | F33: 72 | G33: 77.5 | H33: 63.5 | I33: 41.3 | J33: 68.2 | K33: 75 | L33: =IFERROR((F33*$C$5+G33*$E$5+H33*$G$5+I33*$I$5+J33*$K$5+K33*$M$5)/$O$5,0) -> 68.17 | M33: =RANK(L33,$L$9:$L$84,0) -> 32
A34: Hyundai Palisade | B34: 3-row crossover | C34: T2 | D34: 0.549 | E34: 54.4 | F34: 73.4 | G34: 77.5 | H34: 63.5 | I34: 41.3 | J34: 66.7 | K34: 70.4 | L34: =IFERROR((F34*$C$5+G34*$E$5+H34*$G$5+I34*$I$5+J34*$K$5+K34*$M$5)/$O$5,0) -> 67.53 | M34: =RANK(L34,$L$9:$L$84,0) -> 33
A35: Mazda CX-9 | B35: 3-row crossover | C35: T2 | D35: 0.513 | E35: 56 | F35: 81.1 | G35: 70.5 | H35: 57.8 | I35: 43.5 | J35: 65.2 | K35: 55.6 | L35: =IFERROR((F35*$C$5+G35*$E$5+H35*$G$5+I35*$I$5+J35*$K$5+K35*$M$5)/$O$5,0) -> 65.25 | M35: =RANK(L35,$L$9:$L$84,0) -> 39
A36: Mazda CX-90 | B36: 3-row crossover | C36: T3 | D36: 0.582 | E36: 57.4 | F36: 66.2 | G36: 53.5 | H36: 43.9 | I36: 52.2 | J36: 49.2 | K36: 42.6 | L36: =IFERROR((F36*$C$5+G36*$E$5+H36*$G$5+I36*$I$5+J36*$K$5+K36*$M$5)/$O$5,0) -> 52.61 | M36: =RANK(L36,$L$9:$L$84,0) -> 62
A37: Subaru Ascent | B37: 3-row crossover | C37: T2 | D37: 0.525 | E37: 57.5 | F37: 78.6 | G37: 56.5 | H37: 46.3 | I37: 34.8 | J37: 87.5 | K37: 41.7 | L37: =IFERROR((F37*$C$5+G37*$E$5+H37*$G$5+I37*$I$5+J37*$K$5+K37*$M$5)/$O$5,0) -> 62.305 | M37: =RANK(L37,$L$9:$L$84,0) -> 44
A38: Nissan Pathfinder (2022+) | B38: 3-row crossover | C38: T2 | D38: 0.529 | E38: 56.3 | F38: 77.8 | G38: 77.5 | H38: 63.5 | I38: 37 | J38: 80.4 | K38: 52.8 | L38: =IFERROR((F38*$C$5+G38*$E$5+H38*$G$5+I38*$I$5+J38*$K$5+K38*$M$5)/$O$5,0) -> 68.3 | M38: =RANK(L38,$L$9:$L$84,0) -> 31
A39: Volkswagen Atlas | B39: 3-row crossover | C39: T2 | D39: 0.535 | E39: 53.9 | F39: 76.4 | G39: 77.5 | H39: 63.5 | I39: 37 | J39: 49.6 | K39: 75 | L39: =IFERROR((F39*$C$5+G39*$E$5+H39*$G$5+I39*$I$5+J39*$K$5+K39*$M$5)/$O$5,0) -> 65.12 | M39: =RANK(L39,$L$9:$L$84,0) -> 40
A40: Dodge Durango | B40: 3-row crossover | C40: T2 | D40: 0.561 | E40: 56.5 | F40: 70.8 | G40: 79.2 | H40: 64.9 | I40: 32.6 | J40: 25.4 | K40: 50.9 | L40: =IFERROR((F40*$C$5+G40*$E$5+H40*$G$5+I40*$I$5+J40*$K$5+K40*$M$5)/$O$5,0) -> 55.29 | M40: =RANK(L40,$L$9:$L$84,0) -> 55
A41: Subaru Outback | B41: Mid-size crossover | C41: T2 | D41: 0.483 | E41: 56.7 | F41: 87.6 | G41: 60.9 | H41: 60.9 | I41: 58.7 | J41: 95.5 | K41: 49.1 | L41: =IFERROR((F41*$C$5+G41*$E$5+H41*$G$5+I41*$I$5+J41*$K$5+K41*$M$5)/$O$5,0) -> 72.505 | M41: =RANK(L41,$L$9:$L$84,0) -> 20
A42: Subaru Forester | B42: Compact crossover | C42: T2 | D42: 0.459 | E42: 57.6 | F42: 92.8 | G42: 60.9 | H42: 49.9 | I42: 67.4 | J42: 95.5 | K42: 40.7 | L42: =IFERROR((F42*$C$5+G42*$E$5+H42*$G$5+I42*$I$5+J42*$K$5+K42*$M$5)/$O$5,0) -> 71.765 | M42: =RANK(L42,$L$9:$L$84,0) -> 23
A43: Mazda CX-5 | B43: Compact crossover | C43: T1 | D43: 0.473 | E43: 54.9 | F43: 89.9 | G43: 94.1 | H43: 77.2 | I43: 63 | J43: 65.2 | K43: 65.7 | L43: =IFERROR((F43*$C$5+G43*$E$5+H43*$G$5+I43*$I$5+J43*$K$5+K43*$M$5)/$O$5,0) -> 77.365 | M43: =RANK(L43,$L$9:$L$84,0) -> 11 | N43: Yes
A44: Nissan Rogue | B44: Compact crossover | C44: T3 | D44: 0.459 | E44: 53.8 | F44: 92.7 | G44: 30.1 | H44: 24.7 | I44: 63 | J44: 56.4 | K44: 75.9 | L44: =IFERROR((F44*$C$5+G44*$E$5+H44*$G$5+I44*$I$5+J44*$K$5+K44*$M$5)/$O$5,0) -> 60.36 | M44: =RANK(L44,$L$9:$L$84,0) -> 47 | N44: Yes
A45: Hyundai Tucson | B45: Compact crossover | C45: T2 | D45: 0.457 | E45: 55.5 | F45: 93.3 | G45: 76.1 | H45: 62.4 | I45: 58.7 | J45: 64.7 | K45: 60.2 | L45: =IFERROR((F45*$C$5+G45*$E$5+H45*$G$5+I45*$I$5+J45*$K$5+K45*$M$5)/$O$5,0) -> 71.94 | M45: =RANK(L45,$L$9:$L$84,0) -> 22
A46: Hyundai Santa Fe | B46: Mid-size crossover | C46: T2 | D46: 0.486 | E46: 58.4 | F46: 87.1 | G46: 60 | H46: 49.2 | I46: 50 | J46: 64.7 | K46: 33.3 | L46: =IFERROR((F46*$C$5+G46*$E$5+H46*$G$5+I46*$I$5+J46*$K$5+K46*$M$5)/$O$5,0) -> 61.09 | M46: =RANK(L46,$L$9:$L$84,0) -> 46
A47: Kia Sportage | B47: Compact crossover | C47: T2 | D47: 0.45 | E47: 54.4 | F47: 94.7 | G47: 76.1 | H47: 62.4 | I47: 58.7 | J47: 66.2 | K47: 70.4 | L47: =IFERROR((F47*$C$5+G47*$E$5+H47*$G$5+I47*$I$5+J47*$K$5+K47*$M$5)/$O$5,0) -> 74.12 | M47: =RANK(L47,$L$9:$L$84,0) -> 19 | N47: Yes
A48: Kia Sorento | B48: 3-row crossover | C48: T2 | D48: 0.486 | E48: 54.3 | F48: 87.1 | G48: 60 | H48: 49.2 | I48: 50 | J48: 66.2 | K48: 71.3 | L48: =IFERROR((F48*$C$5+G48*$E$5+H48*$G$5+I48*$I$5+J48*$K$5+K48*$M$5)/$O$5,0) -> 67.09 | M48: =RANK(L48,$L$9:$L$84,0) -> 34
A49: Ford Edge | B49: Mid-size crossover | C49: T2 | D49: 0.486 | E49: 54.2 | F49: 87.1 | G49: 70.5 | H49: 57.8 | I49: 50 | J49: 62.7 | K49: 72.2 | L49: =IFERROR((F49*$C$5+G49*$E$5+H49*$G$5+I49*$I$5+J49*$K$5+K49*$M$5)/$O$5,0) -> 69.39 | M49: =RANK(L49,$L$9:$L$84,0) -> 27 | N49: Yes
A50: Chevrolet Equinox | B50: Compact crossover | C50: T2 | D50: 0.437 | E50: 58.3 | F50: 97.5 | G50: 70.5 | H50: 57.8 | I50: 58.7 | J50: 53.6 | K50: 34.3 | L50: =IFERROR((F50*$C$5+G50*$E$5+H50*$G$5+I50*$I$5+J50*$K$5+K50*$M$5)/$O$5,0) -> 65.355 | M50: =RANK(L50,$L$9:$L$84,0) -> 37 | N50: Yes
A51: Toyota Venza | B51: Compact crossover | C51: T1 | D51: 0.457 | E51: 55.8 | F51: 93.3 | G51: 100 | H51: 82 | I51: 97.8 | J51: 100 | K51: 57.4 | L51: =IFERROR((F51*$C$5+G51*$E$5+H51*$G$5+I51*$I$5+J51*$K$5+K51*$M$5)/$O$5,0) -> 89.015 | M51: =RANK(L51,$L$9:$L$84,0) -> 2 | N51: Yes
A52: Honda HR-V | B52: Subcompact crossover | C52: T2 | D52: 0.426 | E52: 56.9 | F52: 100 | G52: 63.9 | H52: 52.4 | I52: 67.4 | J52: 89.4 | K52: 47.2 | L52: =IFERROR((F52*$C$5+G52*$E$5+H52*$G$5+I52*$I$5+J52*$K$5+K52*$M$5)/$O$5,0) -> 74.145 | M52: =RANK(L52,$L$9:$L$84,0) -> 18 | N52: Yes
A53: Lexus RX 350 | B53: Luxury mid crossover | C53: T1 | D53: 0.604 | E53: 53.9 | F53: 61.6 | G53: 95.5 | H53: 65 | I53: 58.7 | J53: 90.9 | K53: 75 | L53: =IFERROR((F53*$C$5+G53*$E$5+H53*$G$5+I53*$I$5+J53*$K$5+K53*$M$5)/$O$5,0) -> 74.775 | M53: =RANK(L53,$L$9:$L$84,0) -> 16
A54: Lexus RX Hybrid | B54: Luxury mid crossover | C54: T1 | D54: 0.596 | E54: 53 | F54: 63.4 | G54: 100 | H54: 76.6 | I54: 84.8 | J54: 90.9 | K54: 83.3 | L54: =IFERROR((F54*$C$5+G54*$E$5+H54*$G$5+I54*$I$5+J54*$K$5+K54*$M$5)/$O$5,0) -> 81.495 | M54: =RANK(L54,$L$9:$L$84,0) -> 6 | N54: Yes
A55: Lexus NX Hybrid | B55: Luxury mid crossover | C55: T1 | D55: 0.535 | E55: 56.1 | F55: 76.4 | G55: 100 | H55: 82 | I55: 80.4 | J55: 90.9 | K55: 54.6 | L55: =IFERROR((F55*$C$5+G55*$E$5+H55*$G$5+I55*$I$5+J55*$K$5+K55*$M$5)/$O$5,0) -> 80.81 | M55: =RANK(L55,$L$9:$L$84,0) -> 7
A56: Toyota RAV4 Hybrid | B56: Compact crossover | C56: T1 | D56: 0.471 | E56: 56.4 | F56: 90.2 | G56: 100 | H56: 82 | I56: 84.8 | J56: 100 | K56: 51.9 | L56: =IFERROR((F56*$C$5+G56*$E$5+H56*$G$5+I56*$I$5+J56*$K$5+K56*$M$5)/$O$5,0) -> 86.115 | M56: =RANK(L56,$L$9:$L$84,0) -> 4
A57: Toyota RAV4 (gas) | B57: Compact crossover | C57: T1 | D57: 0.478 | E57: 57.8 | F57: 88.7 | G57: 94.1 | H57: 55.6 | I57: 54.3 | J57: 100 | K57: 38.9 | L57: =IFERROR((F57*$C$5+G57*$E$5+H57*$G$5+I57*$I$5+J57*$K$5+K57*$M$5)/$O$5,0) -> 75.895 | M57: =RANK(L57,$L$9:$L$84,0) -> 13
A58: Honda CR-V | B58: Compact crossover | C58: T1 | D58: 0.471 | E58: 58 | F58: 90.2 | G58: 94.1 | H58: 66.2 | I58: 58.7 | J58: 81.4 | K58: 37 | L58: =IFERROR((F58*$C$5+G58*$E$5+H58*$G$5+I58*$I$5+J58*$K$5+K58*$M$5)/$O$5,0) -> 74.295 | M58: =RANK(L58,$L$9:$L$84,0) -> 17
A59: Honda CR-V Hybrid | B59: Compact crossover | C59: T1 | D59: 0.477 | E59: 59.4 | F59: 88.9 | G59: 100 | H59: 82 | I59: 89.1 | J59: 89.4 | K59: 24.1 | L59: =IFERROR((F59*$C$5+G59*$E$5+H59*$G$5+I59*$I$5+J59*$K$5+K59*$M$5)/$O$5,0) -> 79.93 | M59: =RANK(L59,$L$9:$L$84,0) -> 9
A60: Honda Pilot | B60: 3-row crossover | C60: T1 | D60: 0.536 | E60: 58.9 | F60: 76.3 | G60: 89.2 | H60: 77.2 | I60: 32.6 | J60: 89.4 | K60: 25.7 | L60: =IFERROR((F60*$C$5+G60*$E$5+H60*$G$5+I60*$I$5+J60*$K$5+K60*$M$5)/$O$5,0) -> 69.03 | M60: =RANK(L60,$L$9:$L$84,0) -> 28
A61: Ford Escape Hybrid | B61: Compact crossover | C61: T2 | D61: 0.441 | E61: 58.9 | F61: 96.7 | G61: 82 | H61: 67.2 | I61: 100 | J61: 72.7 | K61: 28.7 | L61: =IFERROR((F61*$C$5+G61*$E$5+H61*$G$5+I61*$I$5+J61*$K$5+K61*$M$5)/$O$5,0) -> 75.4 | M61: =RANK(L61,$L$9:$L$84,0) -> 14 | N61: Yes
A62: Hyundai Santa Fe Hybrid | B62: Mid-size crossover | C62: T2 | D62: 0.482 | E62: 56 | F62: 87.9 | G62: 70.5 | H62: 57.8 | I62: 76.1 | J62: 72.7 | K62: 55.6 | L62: =IFERROR((F62*$C$5+G62*$E$5+H62*$G$5+I62*$I$5+J62*$K$5+K62*$M$5)/$O$5,0) -> 71.71 | M62: =RANK(L62,$L$9:$L$84,0) -> 24
A63: Kia Sorento Hybrid | B63: 3-row crossover | C63: T2 | D63: 0.479 | E63: 54.3 | F63: 88.6 | G63: 70.5 | H63: 57.8 | I63: 80.4 | J63: 74.2 | K63: 71.3 | L63: =IFERROR((F63*$C$5+G63*$E$5+H63*$G$5+I63*$I$5+J63*$K$5+K63*$M$5)/$O$5,0) -> 74.97 | M63: =RANK(L63,$L$9:$L$84,0) -> 15 | N63: Yes
A64: Toyota Sienna Hybrid | B64: Minivan | C64: T1 | D64: 0.525 | E64: 56.3 | F64: 78.5 | G64: 100 | H64: 62 | I64: 87 | J64: 100 | K64: 52.8 | L64: =IFERROR((F64*$C$5+G64*$E$5+H64*$G$5+I64*$I$5+J64*$K$5+K64*$M$5)/$O$5,0) -> 80.545 | M64: =RANK(L64,$L$9:$L$84,0) -> 8
A65: Toyota Crown Signia | B65: Mid-size crossover | C65: T2 | D65: 0.565 | E65: 54.3 | F65: 70 | G65: 82 | H65: 67.2 | I65: 93.5 | J65: 100 | K65: 71.3 | L65: =IFERROR((F65*$C$5+G65*$E$5+H65*$G$5+I65*$I$5+J65*$K$5+K65*$M$5)/$O$5,0) -> 79.925 | M65: =RANK(L65,$L$9:$L$84,0) -> 10 | N65: Yes
A66: Toyota Tacoma (pre-2024 V6) | B66: Midsize truck | C66: T1 | D66: 0.565 | E66: 58.1 | F66: 70 | G66: 95.5 | H66: 76.6 | I66: 23.9 | J66: 100 | K66: 22.1 | L66: =IFERROR((F66*$C$5+G66*$E$5+H66*$G$5+I66*$I$5+J66*$K$5+K66*$M$5)/$O$5,0) -> 69.02 | M66: =RANK(L66,$L$9:$L$84,0) -> 29
A67: Toyota Tacoma Hybrid (i-Force Max) | B67: Midsize truck | C67: T3 | D67: 0.615 | E67: 58.1 | F67: 59.3 | G67: 52.5 | H67: 43 | I67: 32.6 | J67: 85 | K67: 24.1 | L67: =IFERROR((F67*$C$5+G67*$E$5+H67*$G$5+I67*$I$5+J67*$K$5+K67*$M$5)/$O$5,0) -> 53.025 | M67: =RANK(L67,$L$9:$L$84,0) -> 60
A68: Toyota 4Runner | B68: Body-on-frame SUV | C68: T1 | D68: 0.605 | E68: 57.1 | F68: 61.3 | G68: 95.5 | H68: 93.1 | I68: 15.2 | J68: 100 | K68: 34.4 | L68: =IFERROR((F68*$C$5+G68*$E$5+H68*$G$5+I68*$I$5+J68*$K$5+K68*$M$5)/$O$5,0) -> 70.295 | M68: =RANK(L68,$L$9:$L$84,0) -> 25 | N68: Yes
A69: Toyota Tundra (2007-2021 5.7 V8) | B69: Full-size truck | C69: T1 | D69: 0.649 | E69: 55.6 | F69: 51.8 | G69: 95.5 | H69: 90.8 | I69: 8.7 | J69: 100 | K69: 53.3 | L69: =IFERROR((F69*$C$5+G69*$E$5+H69*$G$5+I69*$I$5+J69*$K$5+K69*$M$5)/$O$5,0) -> 69.76 | M69: =RANK(L69,$L$9:$L$84,0) -> 26
A70: Chevrolet Silverado 1500 | B70: Full-size truck | C70: T1 | D70: 0.592 | E70: 56.7 | F70: 64.2 | G70: 90.2 | H70: 69.1 | I70: 15.2 | J70: 45.6 | K70: 43.1 | L70: =IFERROR((F70*$C$5+G70*$E$5+H70*$G$5+I70*$I$5+J70*$K$5+K70*$M$5)/$O$5,0) -> 57.05 | M70: =RANK(L70,$L$9:$L$84,0) -> 52
A71: GMC Sierra 1500 | B71: Full-size truck | C71: T1 | D71: 0.605 | E71: 55.3 | F71: 61.4 | G71: 90.2 | H71: 56 | I71: 15.2 | J71: 29 | K71: 56 | L71: =IFERROR((F71*$C$5+G71*$E$5+H71*$G$5+I71*$I$5+J71*$K$5+K71*$M$5)/$O$5,0) -> 53 | M71: =RANK(L71,$L$9:$L$84,0) -> 61
A72: Ford F-150 | B72: Full-size truck | C72: T2 | D72: 0.592 | E72: 55.3 | F72: 64.1 | G72: 58.2 | H72: 57.2 | I72: 13 | J72: 60.7 | K72: 56 | L72: =IFERROR((F72*$C$5+G72*$E$5+H72*$G$5+I72*$I$5+J72*$K$5+K72*$M$5)/$O$5,0) -> 55.175 | M72: =RANK(L72,$L$9:$L$84,0) -> 56
A73: Ford F-150 Hybrid (PowerBoost) | B73: Full-size truck | C73: T2 | D73: 0.612 | E73: 52.4 | F73: 59.8 | G73: 50.2 | H73: 41.2 | I73: 37 | J73: 54.7 | K73: 82.9 | L73: =IFERROR((F73*$C$5+G73*$E$5+H73*$G$5+I73*$I$5+J73*$K$5+K73*$M$5)/$O$5,0) -> 55.735 | M73: =RANK(L73,$L$9:$L$84,0) -> 54
A74: Ram 1500 | B74: Full-size truck | C74: T2 | D74: 0.609 | E74: 54.2 | F74: 60.4 | G74: 79.2 | H74: 37.1 | I74: 19.6 | J74: 21.4 | K74: 66.2 | L74: =IFERROR((F74*$C$5+G74*$E$5+H74*$G$5+I74*$I$5+J74*$K$5+K74*$M$5)/$O$5,0) -> 48.715 | M74: =RANK(L74,$L$9:$L$84,0) -> 68
A75: Ford Ranger | B75: Midsize truck | C75: T2 | D75: 0.534 | E75: 58.9 | F75: 76.6 | G75: 51.2 | H75: 49.5 | I75: 41.3 | J75: 60.7 | K75: 22.7 | L75: =IFERROR((F75*$C$5+G75*$E$5+H75*$G$5+I75*$I$5+J75*$K$5+K75*$M$5)/$O$5,0) -> 53.93 | M75: =RANK(L75,$L$9:$L$84,0) -> 59
A76: Chevrolet Colorado | B76: Midsize truck | C76: T2 | D76: 0.521 | E76: 57.4 | F76: 79.4 | G76: 77.5 | H76: 54.4 | I76: 41.3 | J76: 63.6 | K76: 36.6 | L76: =IFERROR((F76*$C$5+G76*$E$5+H76*$G$5+I76*$I$5+J76*$K$5+K76*$M$5)/$O$5,0) -> 61.975 | M76: =RANK(L76,$L$9:$L$84,0) -> 45
A77: GMC Canyon | B77: Midsize truck | C77: T2 | D77: 0.525 | E77: 58.8 | F77: 78.6 | G77: 77.5 | H77: 59 | I77: 41.3 | J77: 47 | K77: 23.6 | L77: =IFERROR((F77*$C$5+G77*$E$5+H77*$G$5+I77*$I$5+J77*$K$5+K77*$M$5)/$O$5,0) -> 57.195 | M77: =RANK(L77,$L$9:$L$84,0) -> 51
A78: Nissan Frontier (2022+) | B78: Midsize truck | C78: T1 | D78: 0.538 | E78: 55.1 | F78: 75.7 | G78: 95.5 | H78: 46 | I78: 28.3 | J78: 86.4 | K78: 57.9 | L78: =IFERROR((F78*$C$5+G78*$E$5+H78*$G$5+I78*$I$5+J78*$K$5+K78*$M$5)/$O$5,0) -> 68.945 | M78: =RANK(L78,$L$9:$L$84,0) -> 30
A79: Nissan Titan | B79: Full-size truck | C79: T2 | D79: 0.579 | E79: 56.7 | F79: 67 | G79: 77.5 | H79: 63.1 | I79: 15.2 | J79: 86.4 | K79: 43.1 | L79: =IFERROR((F79*$C$5+G79*$E$5+H79*$G$5+I79*$I$5+J79*$K$5+K79*$M$5)/$O$5,0) -> 63.105 | M79: =RANK(L79,$L$9:$L$84,0) -> 43
A80: Honda Ridgeline | B80: Midsize truck | C80: T1 | D80: 0.519 | E80: 57 | F80: 79.8 | G80: 89.2 | H80: 73 | I80: 41.3 | J80: 89.4 | K80: 40.3 | L80: =IFERROR((F80*$C$5+G80*$E$5+H80*$G$5+I80*$I$5+J80*$K$5+K80*$M$5)/$O$5,0) -> 72.335 | M80: =RANK(L80,$L$9:$L$84,0) -> 21
... A84: Ram 2500 (Cummins) | B84: Heavy-duty truck | C84: T2 | D84: 0.804 | E84: 57.8 | F84: 18.4 | G84: 74.5 | H84: 77.1 | I84: 15.2 | J84: 33.4 | K84: 32.9 | L84: =IFERROR((F84*$C$5+G84*$E$5+H84*$G$5+I84*$I$5+J84*$K$5+K84*$M$5)/$O$5,0) -> 40.475 | M84: =RANK(L84,$L$9:$L$84,0) -> 73
A86: - 'Undominated' now tests all SIX axes. Only a handful of vehicles survive that - everything else is beaten on every dimension at once by something on the list.
A87: - Comfort is derived from measured interior-noise readings at 55 mph (median across the trims that were tested), minus points for documented seat complaints and body-on-frame ride harshness. Column E flags which readings are real measurements. This is the best-sourced of the three subjective axes.
A88: - Reliability is a SWAG: Consumer Reports brand record rescaled, minus penalties for documented mid-life failure patterns (GM AFM lifters, Ram Hemi MDS, Ford 10R80 and cam phasers, Jatco CVT, ZF 9HP, Theta II, the Toyota V35A recall). It is not measured failure data. Replace it with NHTSA data if you want rigor - see the Sources tab.
A89: - Quality is my own construct: 45% tier judgment, 35% transmission record, 20% engine architecture. It overlaps with Reliability by design. If you weight both heavily you are double-counting drivetrain risk.

Sheet StrategyMatrix
A1: Strategy Matrix
A2: Each row is a different way of caring about the problem. The winner is what that strategy picks.
A4: Strategy | B4: What it optimizes for | C4: Cost | D4: Qual | E4: Long | F4: Eff | G4: Rel | H4: Comf | I4: Restricted to | J4: WINNER | K4: Score | L4: $/mile | M4: Tier | N4: Cabin dB | O4: Runner-up | P4: Third
A5: Minimum cost | B5: Cheapest per mile. Nothing else counted. | C5: 100 | D5: 0 | E5: 0 | F5: 0 | G5: 0 | H5: 0 | I5: - | J5: Honda HR-V | K5: 100 | L5: 0.426 | M5: T2 | N5: 56.9 | O5: Chevrolet Equinox | P5: Ford Escape Hybrid
A6: Maximum quality | B6: Best drivetrain architecture. Price ignored. | C6: 0 | D6: 100 | E6: 0 | F6: 0 | G6: 0 | H6: 0 | I6: - | J6: Toyota Grand Highlander Hybrid | K6: 100 | L6: 0.58 | M6: T1 | N6: 51.2 | O6: Toyota Highlander Hybrid | P6: Toyota Venza
A7: Maximum longevity | B7: Most likely to pass 250,000 miles. | C7: 0 | D7: 0 | E7: 100 | F7: 0 | G7: 0 | H7: 0 | I7: - | J7: Toyota Sequoia (pre-2023 5.7 V8) | K7: 97.4 | L7: 0.717 | M7: T1 | N7: 55.7 | O7: Toyota 4Runner | P7: Toyota Highlander Hybrid
A8: Maximum efficiency | B8: Highest real highway MPG. | C8: 0 | D8: 0 | E8: 0 | F8: 100 | G8: 0 | H8: 0 | I8: - | J8: Ford Escape Hybrid | K8: 100 | L8: 0.441 | M8: T2 | N8: 58.9 | O8: Toyota Venza | P8: Toyota Crown Signia
A9: Maximum reliability | B9: Best brand record, fewest documented failure patterns. | C9: 0 | D9: 0 | E9: 0 | F9: 0 | G9: 100 | H9: 0 | I9: - | J9: Toyota Sequoia (pre-2023 5.7 V8) | K9: 100 | L9: 0.717 | M9: T1 | N9: 55.7 | O9: Toyota Grand Highlander Hybrid | P9: Toyota Highlander (gas)
A10: Maximum comfort | B10: Quietest cabin, best seat and ride. | C10: 0 | D10: 0 | E10: 0 | F10: 0 | G10: 0 | H10: 100 | I10: - | J10: Toyota Grand Highlander Hybrid | K10: 100 | L10: 0.58 | M10: T1 | N10: 51.2 | O10: Toyota Highlander (gas) | P10: Toyota Highlander Hybrid
A11: Balanced six | B11: All six axes, cost weighted highest. | C11: 25 | D11: 15 | E11: 15 | F11: 10 | G11: 20 | H11: 15 | I11: - | J11: Toyota Highlander Hybrid | K11: 89.9 | L11: 0.517 | M11: T1 | N11: 52.6 | O11: Toyota Venza | P11: Toyota Grand Highlander Hybrid
A12: Balanced thirds | B12: The original three axes, equally. | C12: 33 | D12: 34 | E12: 33 | F12: 0 | G12: 0 | H12: 0 | I12: - | J12: Toyota Venza | K12: 91.8 | L12: 0.457 | M12: T1 | N12: 55.8 | O12: Ford Maverick Hybrid | P12: Toyota RAV4 Hybrid
A13: Cost + comfort | B13: Cheap and quiet. Ignores whether it lasts. | C13: 50 | D13: 0 | E13: 0 | F13: 0 | G13: 0 | H13: 50 | I13: - | J13: Nissan Rogue | K13: 84.3 | L13: 0.459 | M13: T3 | N13: 53.8 | O13: Toyota Highlander Hybrid | P13: Toyota Grand Highlander Hybrid
A14: Cost + reliability | B14: Cheap and unlikely to break. | C14: 50 | D14: 0 | E14: 0 | F14: 0 | G14: 50 | H14: 0 | I14: - | J14: Toyota Venza | K14: 96.7 | L14: 0.457 | M14: T1 | N14: 55.8 | O14: Toyota RAV4 Hybrid | P14: Honda HR-V
A15: Run it forever | B15: Durability only. Price is not the constraint. | C15: 0 | D15: 30 | E15: 40 | F15: 0 | G15: 30 | H15: 0 | I15: - | J15: Toyota Sequoia (pre-2023 5.7 V8) | K15: 97.6 | L15: 0.717 | M15: T1 | N15: 55.7 | O15: Toyota Highlander Hybrid | P15: Toyota 4Runner
A16: Butt in seat | B16: For 1,100 hours a year in the driver's seat. | C16: 15 | D16: 10 | E16: 10 | F16: 5 | G16: 20 | H16: 40 | I16: - | J16: Toyota Grand Highlander Hybrid | K16: 91.8 | L16: 0.58 | M16: T1 | N16: 51.2 | O16: Toyota Highlander Hybrid | P16: Toyota Highlander (gas)
... A24: Three-row, balanced | B24: Balanced six, three-row family haulers only. | C24: 25 | D24: 15 | E24: 15 | F24: 10 | G24: 20 | H24: 15 | I24: Three-row / minivan | J24: Toyota Highlander Hybrid | K24: 89.9 | L24: 0.517 | M24: T1 | N24: 52.6 | O24: Toyota Grand Highlander Hybrid | P24: Toyota Highlander (gas)
A26: HOW TO READ THIS
A27: - Static snapshots at the default Inputs. Change the Inputs tab and the Models tab moves, but this matrix does not recompute - use the Scoring tab or the interactive HTML tool for live results.
A28: - The same vehicle winning many rows is the signal. It means the choice is robust: it does not depend on how you weight the trade-offs, so you never have to settle the philosophical question of what matters most.
A29: - Where a strategy picks a Tier 3 vehicle, the strategy is wrong for a 180,000-mile plan, not the data. 'Cost + comfort' will happily recommend a quiet crossover with a transmission that will not survive the ownership period. That is what it was asked to do.
A30: - Quality and Reliability overlap on purpose. Weighting both at maximum double-counts drivetrain risk. Pick one as your primary durability axis.

Sheet Sources
B1: Sources & Source Quality
B2: Every material number in this workbook, with a note on how much weight it deserves.
B4: Figure | C4: Source | D4: Confidence
B5: Depreciation by odometer band | C5: ForCar (Aug 2026), pooled analysis of ~327,000 US used listings. Median price by band; ~$1,615 lost per 10,000 miles on average. | D5: Medium — asking-price cross-sections, not tracked VINs
B6: Depreciation theory | C6: Sallee, West & Knittel, 'Automobile Depreciation', NBER Working Paper w21441. Establishes separate age and mileage components; notes a simple polynomial fits poorly at high odometer. | D6: High — peer-reviewed
B7: Depreciation slowdown past 110k | C7: Auto Express / Carwow analysis. | D7: Medium — UK market
B8: First-year depreciation ~20% | C8: Kelley Blue Book depreciation calculator. | D8: Medium — KBB sells vehicle valuations
B9: Total ownership cost benchmark | C9: AAA 'Your Driving Costs' (released 9/16/2025): average $4,334/yr depreciation, down from $4,680 in 2024; total $11,577/yr or $964.78/mo. | D9: High — but assumes 15,000 mi/yr, not 55,000
B10: Indiana fuel prices | C10: AAA via WWBL, early Aug 2026: $3.55 regular, $5.35 diesel. National average $4.06-$4.11. | D10: High — daily survey
B11: Tire tread life | C11: Consumer Reports treadwear testing: 70,000-100,000 miles for premium touring tires. | D11: High — independent testing
B12: Maintenance cost curve | C12: YourMechanic: ~$1,400 to reach 25,000 miles, costs rise rapidly to 100,000. | D12: Medium
B13: Major repair incidence | C13: CoverageX: ~2/3 of vehicles over 100k miles hit a major repair averaging $3,847 within 12 months. | D13: LOW — extended warranty seller, obvious bias. Treat as a ceiling.
B14: Repair cost ranges | C14: Aggregated: transmission rebuild $2,000-$5,500; suspension overhaul $2,000-$3,500; AC compressor $1,800-$2,800; catalytic converter $1,500-$2,500. | D14: Medium
B15: Indiana insurance | C15: Insure.com $1,856; CarInsurance.com $1,515; Experian $1,694; MoneyGeek $1,009. Spread reflects methodology differences. | D15: Medium — wide spread, get a real quote
... B38: CONFLICTING FUEL PRICE | C38: Two research passes returned different Indiana gas prices for mid-2026: $3.55/gal (AAA via WWBL, early Aug 2026, with a specific date and outlet) and ~$3.10/gal (less specifically sourced). The workbook uses $3.55 as the more precisely attributed figure. This is an input cell — flex it. At $3.10 the full-size SUV fuel penalty narrows from ~$4,500/yr to ~$3,900/yr and every ranking shifts toward the thirstier vehicles. | D38: FLAGGED CONFLICT — sources disagree
B40: Sources deliberately discounted: dealer Section 179 landing pages (marketing), CarMax/Carvana/Vroom content (they profit from turnover frequency), extended-warranty vendors (they profit from repair anxiety), and affiliate-monetized 'best cars' listicles. Where a claim from one of these was used, it was cross-checked against a primary source or flagged above.
